sim/v003_icg_fixed/icg_cell_neg.v
///////////////////////////////////////////
// icg_cell_neg.v — ICG cell for NEGEDGE-triggered flip-flops
//
// Standard ICG uses a neg-level latch for posedge FFs.
// Wally's regfile writes on negedge clk, so we need a
// POSITIVE-level latch: transparent when clk is HIGH,
// holds when clk is LOW. This lets we3 propagate through
// during the HIGH phase, so the gated falling edge arrives
// correctly.
///////////////////////////////////////////

module icg_cell_neg (
  input  wire clk_in,
  input  wire enable,
  input  wire test_en,
  output wire clk_out
);

  reg en_latch;

  // Positive level-sensitive latch
  // Transparent when clk_in is HIGH, holds when clk_in is LOW
  always @(*) begin
    if (clk_in)
      en_latch = enable | test_en;
  end

  // Gated clock: passes falling edge only when enabled
  assign clk_out = clk_in & en_latch;

endmodule

sim/v003_icg_fixed/regfile_icg.v
///////////////////////////////////////////
// regfile_icg.v — v003: ICG-gated regfile with fixed latch polarity
///////////////////////////////////////////

module regfile_icg #(
  parameter XLEN = 32,
  parameter E_SUPPORTED = 0
) (
  input  wire             clk,
  input  wire             reset,
  input  wire             we3,
  input  wire [4:0]       a1, a2, a3,
  input  wire [XLEN-1:0]  wd3,
  output wire [XLEN-1:0]  rd1, rd2
);

  localparam NUMREGS = E_SUPPORTED ? 16 : 32;

  reg [XLEN-1:0] rf [1:NUMREGS-1];
  integer i;

  wire rf_clk_en = we3 | reset;
  wire gated_clk;

  icg_cell_neg u_icg (
    .clk_in  (clk),
    .enable  (rf_clk_en),
    .test_en (1'b0),
    .clk_out (gated_clk)
  );

  always @(negedge gated_clk) begin
    if (reset) begin
      for (i = 1; i < NUMREGS; i = i + 1)
        rf[i] <= {XLEN{1'b0}};
    end else begin
      if (we3 && a3 != 0)
        rf[a3] <= wd3;
    end
  end

  assign rd1 = (a1 != 0) ? rf[a1] : {XLEN{1'b0}};
  assign rd2 = (a2 != 0) ? rf[a2] : {XLEN{1'b0}};

endmodule

sim/v003_icg_fixed/tb_debug.v
///////////////////////////////////////////
// tb_debug.v — Minimal debug testbench to trace ICG timing
///////////////////////////////////////////
`timescale 1ns/1ps

module tb_debug;
  reg clk, reset, we3;
  reg [4:0] a1, a3;
  reg [31:0] wd3;
  wire [31:0] rd1, rd2;

  initial clk = 0;
  always #5 clk = ~clk;

  regfile_icg #(.XLEN(32), .E_SUPPORTED(0)) dut (
    .clk(clk), .reset(reset), .we3(we3),
    .a1(a1), .a2(5'd0), .a3(a3),
    .wd3(wd3), .rd1(rd1), .rd2(rd2)
  );

  initial begin
    $dumpfile("debug.vcd");
    $dumpvars(0, tb_debug);

    reset = 1; we3 = 0; a1 = 0; a3 = 0; wd3 = 0;

    // Reset
    repeat(4) @(posedge clk);
    reset = 0;

    // Write x1 = 0xCAFEBABE
    // Setup data BEFORE posedge, so it's stable for the negedge write
    @(posedge clk);
    we3 = 1;
    a3 = 5'd1;
    wd3 = 32'hCAFEBABE;
    $display("t=%0t: Set we3=1, a3=1, wd3=0xCAFEBABE", $time);
    $display("t=%0t: clk=%b gated_clk=%b en_latch=%b", $time, clk, dut.gated_clk, dut.u_icg.en_latch);

    @(negedge clk);
    $display("t=%0t: NEGEDGE clk. clk=%b gated_clk=%b en_latch=%b", $time, clk, dut.gated_clk, dut.u_icg.en_latch);

    @(posedge clk);
    $display("t=%0t: POSEDGE clk. clk=%b gated_clk=%b en_latch=%b rf[1]=%h", $time, clk, dut.gated_clk, dut.u_icg.en_latch, dut.rf[1]);

    // Now read back
    we3 = 0;
    a1 = 5'd1;
    #1;
    $display("t=%0t: READ rd1=%h (expect CAFEBABE)", $time, rd1);

    // Try again: set we3 one full cycle earlier
    @(posedge clk);
    @(posedge clk);
    we3 = 1;
    a3 = 5'd2;
    wd3 = 32'hDEAD_BEEF;
    $display("t=%0t: Set we3=1 for x2", $time);

    // Wait for the negedge to actually write
    @(negedge clk);
    $display("t=%0t: NEGEDGE. gated_clk=%b en_latch=%b", $time, dut.gated_clk, dut.u_icg.en_latch);
    #1;
    $display("t=%0t: After negedge settle. gated_clk=%b rf[2]=%h", $time, dut.gated_clk, dut.rf[2]);

    @(posedge clk);
    we3 = 0;
    a1 = 5'd2;
    #1;
    $display("t=%0t: READ rd1=%h (expect DEADBEEF)", $time, rd1);

    #50;
    $finish;
  end
endmodule

sim/v003_icg_fixed/debug.vcd
$date
	Tue Jul 21 13:18:05 2026
$end
$version
	Icarus Verilog
$end
$timescale
	1ps
$end
$scope module tb_debug $end
$var wire 32 ! rd2 [31:0] $end
$var wire 32 " rd1 [31:0] $end
$var reg 5 # a1 [4:0] $end
$var reg 5 $ a3 [4:0] $end
$var reg 1 % clk $end
$var reg 1 & reset $end
$var reg 32 ' wd3 [31:0] $end
$var reg 1 ( we3 $end
$scope module dut $end
$var wire 5 ) a1 [4:0] $end
$var wire 5 * a2 [4:0] $end
$var wire 5 + a3 [4:0] $end
$var wire 1 % clk $end
$var wire 1 & reset $end
$var wire 1 , rf_clk_en $end
$var wire 32 - wd3 [31:0] $end
$var wire 1 ( we3 $end
$var wire 32 . rd2 [31:0] $end
$var wire 32 / rd1 [31:0] $end
$var wire 1 0 gated_clk $end
$var integer 32 1 i [31:0] $end
$scope module u_icg $end
$var wire 1 % clk_in $end
$var wire 1 0 clk_out $end
$var wire 1 , enable $end
$var wire 1 2 test_en $end
$var reg 1 3 en_latch $end
$upscope $end
$upscope $end
$upscope $end
$enddefinitions $end
#0
$dumpvars
x3
02
b100000 1
00
b0 /
b0 .
b0 -
1,
b0 +
b0 *
b0 )
0(
b0 '
1&
0%
b0 $
b0 #
b0 "
b0 !
$end
#5000
10
13
1%
#10000
b100000 1
00
0%
#15000
10
1%
#20000
b100000 1
00
0%
#25000
10
1%
#30000
b100000 1
00
0%
#35000
03
0,
00
0&
1%
#40000
0%
#45000
10
13
1,
b11001010111111101011101010111110 '
b11001010111111101011101010111110 -
b1 $
b1 +
1(
1%
#50000
00
0%
#55000
03
b11001010111111101011101010111110 "
b11001010111111101011101010111110 /
0,
00
b1 #
b1 )
0(
1%
#60000
0%
#65000
1%
#70000
0%
#75000
10
13
1,
b11011110101011011011111011101111 '
b11011110101011011011111011101111 -
b10 $
b10 +
1(
1%
#80000
00
0%
#85000
03
b11011110101011011011111011101111 "
b11011110101011011011111011101111 /
0,
00
b10 #
b10 )
0(
1%
