sim/v003_icg_fixed/icg_cell_neg.v
///////////////////////////////////////////
// icg_cell_neg.v — ICG cell for NEGEDGE-triggered flip-flops
//
// Standard ICG uses a neg-level latch for posedge FFs.
// Wally's regfile writes on negedge clk, so we need a
// POSITIVE-level latch: transparent when clk is HIGH,
// holds when clk is LOW. This lets we3 propagate through
// during the HIGH phase, so the gated falling edge arrives
// correctly.
///////////////////////////////////////////

module icg_cell_neg (
  input  wire clk_in,
  input  wire enable,
  input  wire test_en,
  output wire clk_out
);

  reg en_latch;

  // Positive level-sensitive latch
  // Transparent when clk_in is HIGH, holds when clk_in is LOW
  always @(*) begin
    if (clk_in)
      en_latch = enable | test_en;
  end

  // Gated clock: passes falling edge only when enabled
  assign clk_out = clk_in & en_latch;

endmodule

sim/v003_icg_fixed/regfile_icg.v
///////////////////////////////////////////
// regfile_icg.v — v003: ICG-gated regfile with fixed latch polarity
///////////////////////////////////////////

module regfile_icg #(
  parameter XLEN = 32,
  parameter E_SUPPORTED = 0
) (
  input  wire             clk,
  input  wire             reset,
  input  wire             we3,
  input  wire [4:0]       a1, a2, a3,
  input  wire [XLEN-1:0]  wd3,
  output wire [XLEN-1:0]  rd1, rd2
);

  localparam NUMREGS = E_SUPPORTED ? 16 : 32;

  reg [XLEN-1:0] rf [1:NUMREGS-1];
  integer i;

  wire rf_clk_en = we3 | reset;
  wire gated_clk;

  icg_cell_neg u_icg (
    .clk_in  (clk),
    .enable  (rf_clk_en),
    .test_en (1'b0),
    .clk_out (gated_clk)
  );

  always @(negedge gated_clk) begin
    if (reset) begin
      for (i = 1; i < NUMREGS; i = i + 1)
        rf[i] <= {XLEN{1'b0}};
    end else begin
      if (we3 && a3 != 0)
        rf[a3] <= wd3;
    end
  end

  assign rd1 = (a1 != 0) ? rf[a1] : {XLEN{1'b0}};
  assign rd2 = (a2 != 0) ? rf[a2] : {XLEN{1'b0}};

endmodule

sim/v003_icg_fixed/tb_regfile_icg.v
///////////////////////////////////////////
// tb_regfile_icg.v — v003: Fixed testbench timing for ICG regfile
//
// KEY INSIGHT FROM BUG-001 DEBUG:
// The ICG cell needs we3 to be stable during the HIGH phase of clk
// so the latch can capture it. In a real pipeline, RegWriteW is
// computed by combinational logic and stable well before the edge.
// The testbench must mimic this: drive we3 at posedge, not negedge.
///////////////////////////////////////////
`timescale 1ns/1ps

module tb_regfile_icg;

  parameter XLEN = 32;
  parameter E_SUPPORTED = 0;

  reg              clk, reset;
  reg              we3;
  reg  [4:0]       a1, a2, a3;
  reg  [XLEN-1:0]  wd3;
  wire [XLEN-1:0]  rd1, rd2;

  initial clk = 0;
  always #5 clk = ~clk;

  regfile_icg #(.XLEN(XLEN), .E_SUPPORTED(E_SUPPORTED)) dut (
    .clk(clk), .reset(reset), .we3(we3),
    .a1(a1), .a2(a2), .a3(a3),
    .wd3(wd3), .rd1(rd1), .rd2(rd2)
  );

  integer write_cycles, idle_cycles, total_cycles, gated_toggles, errors;
  integer i;

  // Count gated clock negedges (actual FF toggle events)
  always @(negedge dut.gated_clk) begin
    if (!reset)
      gated_toggles = gated_toggles + 1;
  end

  initial begin
    $dumpfile("v003_icg_fixed.vcd");
    $dumpvars(0, tb_regfile_icg);

    write_cycles = 0; idle_cycles = 0;
    total_cycles = 0; gated_toggles = 0; errors = 0;
    reset = 1; we3 = 0;
    a1 = 0; a2 = 0; a3 = 0; wd3 = 0;

    repeat(4) @(posedge clk);
    reset = 0;

    $display("========================================");
    $display("v003 ICG-FIXED REGFILE SIMULATION");
    $display("========================================");

    // TEST 1: Write all 31 registers
    // Drive we3 at posedge so ICG latch captures it during HIGH phase.
    // The write happens on the negedge of gated_clk within the same cycle.
    $display("[TEST 1] Writing x1-x31...");
    for (i = 1; i < 32; i = i + 1) begin
      @(posedge clk);
      we3 = 1;
      a3 = i[4:0];
      wd3 = 32'hA000_0000 + i;
      write_cycles = write_cycles + 1;
      total_cycles = total_cycles + 1;
    end
    @(posedge clk);
    we3 = 0;
    total_cycles = total_cycles + 1;
    idle_cycles = idle_cycles + 1;

    // TEST 2: Read back all registers
    $display("[TEST 2] Read-back verification...");
    for (i = 1; i < 32; i = i + 1) begin
      a1 = i[4:0];
      a2 = 5'd0;
      #1;
      if (rd1 !== (32'hA000_0000 + i)) begin
        $display("  FAIL: x%0d = 0x%08h, want 0x%08h", i, rd1, 32'hA000_0000 + i);
        errors = errors + 1;
      end
      if (rd2 !== 32'h0) begin
        $display("  FAIL: x0 = 0x%08h, want 0", rd2);
        errors = errors + 1;
      end
      @(posedge clk);
      idle_cycles = idle_cycles + 1;
      total_cycles = total_cycles + 1;
    end

    // TEST 3: Interleaved write/read stress
    $display("[TEST 3] Write/read stress x1-x15...");
    for (i = 1; i < 16; i = i + 1) begin
      // Write cycle
      @(posedge clk);
      we3 = 1;
      a3 = i[4:0];
      wd3 = 32'hDEAD_0000 + i;
      write_cycles = write_cycles + 1;
      total_cycles = total_cycles + 1;

      // Read-back cycle (next posedge)
      @(posedge clk);
      we3 = 0;
      a1 = i[4:0];
      #1;
      if (rd1 !== (32'hDEAD_0000 + i)) begin
        $display("  FAIL: x%0d = 0x%08h, want 0x%08h", i, rd1, 32'hDEAD_0000 + i);
        errors = errors + 1;
      end
      idle_cycles = idle_cycles + 1;
      total_cycles = total_cycles + 1;
    end

    // TEST 4: 50 idle cycles — gated_clk should NOT toggle
    $display("[TEST 4] 50 idle cycles...");
    we3 = 0; a1 = 5'd1; a2 = 5'd2;
    repeat(50) begin
      @(posedge clk);
      idle_cycles = idle_cycles + 1;
      total_cycles = total_cycles + 1;
    end

    // Results
    $display("========================================");
    $display("v003 RESULTS");
    $display("========================================");
    $display("Total cycles:            %0d", total_cycles);
    $display("Write cycles (we3=1):    %0d", write_cycles);
    $display("Idle cycles (we3=0):     %0d", idle_cycles);
    $display("Gated clk toggles:       %0d", gated_toggles);
    $display("Write activity:          %0d%%", (write_cycles * 100) / total_cycles);
    $display("Clock gating efficiency: %0d%%",
      ((total_cycles - gated_toggles) * 100) / total_cycles);
    $display("Errors:                  %0d", errors);
    $display("STATUS: %s", errors == 0 ? "PASS" : "FAIL");
    $display("========================================");

    #20; $finish;
  end
endmodule

sim/v003_icg_fixed/v003_icg_fixed.vcd
$date
	Tue Jul 21 13:21:58 2026
$end
$version
	Icarus Verilog
$end
$timescale
	1ps
$end
$scope module tb_regfile_icg $end
$var wire 32 ! rd2 [31:0] $end
$var wire 32 " rd1 [31:0] $end
$var reg 5 # a1 [4:0] $end
$var reg 5 $ a2 [4:0] $end
$var reg 5 % a3 [4:0] $end
$var reg 1 & clk $end
$var reg 1 ' reset $end
$var reg 32 ( wd3 [31:0] $end
$var reg 1 ) we3 $end
$var integer 32 * errors [31:0] $end
$var integer 32 + gated_toggles [31:0] $end
$var integer 32 , i [31:0] $end
$var integer 32 - idle_cycles [31:0] $end
$var integer 32 . total_cycles [31:0] $end
$var integer 32 / write_cycles [31:0] $end
$scope module dut $end
$var wire 5 0 a1 [4:0] $end
$var wire 5 1 a2 [4:0] $end
$var wire 5 2 a3 [4:0] $end
$var wire 1 & clk $end
$var wire 1 ' reset $end
$var wire 1 3 rf_clk_en $end
$var wire 32 4 wd3 [31:0] $end
$var wire 1 ) we3 $end
$var wire 32 5 rd2 [31:0] $end
$var wire 32 6 rd1 [31:0] $end
$var wire 1 7 gated_clk $end
$var integer 32 8 i [31:0] $end
$scope module u_icg $end
$var wire 1 & clk_in $end
$var wire 1 7 clk_out $end
$var wire 1 3 enable $end
$var wire 1 9 test_en $end
$var reg 1 : en_latch $end
$upscope $end
$upscope $end
$upscope $end
$enddefinitions $end
#0
$dumpvars
x:
09
b100000 8
07
b0 6
b0 5
b0 4
13
b0 2
b0 1
b0 0
b0 /
b0 .
b0 -
bx ,
b0 +
b0 *
0)
b0 (
1'
0&
b0 %
b0 $
b0 #
b0 "
b0 !
$end
#5000
17
1:
1&
#10000
b100000 8
07
0&
#15000
17
1&
#20000
b100000 8
07
0&
#25000
17
1&
#30000
b100000 8
07
0&
#35000
b1 +
0:
03
07
b1 ,
0'
1&
#40000
0&
#45000
17
1:
13
b10 ,
b1 .
b1 /
b10100000000000000000000000000001 (
b10100000000000000000000000000001 4
b1 %
b1 2
1)
1&
#50000
b10 +
07
0&
#55000
17
b11 ,
b10 .
b10 /
b10100000000000000000000000000010 (
b10100000000000000000000000000010 4
b10 %
b10 2
1&
#60000
b11 +
07
0&
#65000
17
b100 ,
b11 .
b11 /
b10100000000000000000000000000011 (
b10100000000000000000000000000011 4
b11 %
b11 2
1&
#70000
b100 +
07
0&
#75000
17
b101 ,
b100 .
b100 /
b10100000000000000000000000000100 (
b10100000000000000000000000000100 4
b100 %
b100 2
1&
#80000
b101 +
07
0&
#85000
17
b110 ,
b101 .
b101 /
b10100000000000000000000000000101 (
b10100000000000000000000000000101 4
b101 %
b101 2
1&
#90000
b110 +
07
0&
#95000
17
b111 ,
b110 .
b110 /
b10100000000000000000000000000110 (
b10100000000000000000000000000110 4
b110 %
b110 2
1&
#100000
b111 +
07
0&
#105000
17
b1000 ,
b111 .
b111 /
b10100000000000000000000000000111 (
b10100000000000000000000000000111 4
b111 %
b111 2
1&
#110000
b1000 +
07
0&
#115000
17
b1001 ,
b1000 .
b1000 /
b10100000000000000000000000001000 (
b10100000000000000000000000001000 4
b1000 %
b1000 2
1&
#120000
b1001 +
07
0&
#125000
17
b1010 ,
b1001 .
b1001 /
b10100000000000000000000000001001 (
b10100000000000000000000000001001 4
b1001 %
b1001 2
1&
#130000
b1010 +
07
0&
#135000
17
b1011 ,
b1010 .
b1010 /
b10100000000000000000000000001010 (
b10100000000000000000000000001010 4
b1010 %
b1010 2
1&
#140000
b1011 +
07
0&
#145000
17
b1100 ,
b1011 .
b1011 /
b10100000000000000000000000001011 (
b10100000000000000000000000001011 4
b1011 %
b1011 2
1&
#150000
b1100 +
07
0&
#155000
17
b1101 ,
b1100 .
b1100 /
b10100000000000000000000000001100 (
b10100000000000000000000000001100 4
b1100 %
b1100 2
1&
#160000
b1101 +
07
0&
#165000
17
b1110 ,
b1101 .
b1101 /
b10100000000000000000000000001101 (
b10100000000000000000000000001101 4
b1101 %
b1101 2
1&
#170000
b1110 +
07
0&
#175000
17
b1111 ,
b1110 .
b1110 /
b10100000000000000000000000001110 (
b10100000000000000000000000001110 4
b1110 %
b1110 2
1&
#180000
b1111 +
07
0&
#185000
17
b10000 ,
b1111 .
b1111 /
b10100000000000000000000000001111 (
b10100000000000000000000000001111 4
b1111 %
b1111 2
1&
#190000
b10000 +
07
0&
#195000
17
b10001 ,
b10000 .
b10000 /
b10100000000000000000000000010000 (
b10100000000000000000000000010000 4
b10000 %
b10000 2
1&
#200000
b10001 +
07
0&
#205000
17
b10010 ,
b10001 .
b10001 /
b10100000000000000000000000010001 (
b10100000000000000000000000010001 4
b10001 %
b10001 2
1&
#210000
b10010 +
07
0&
#215000
17
b10011 ,
b10010 .
b10010 /
b10100000000000000000000000010010 (
b10100000000000000000000000010010 4
b10010 %
b10010 2
1&
#220000
b10011 +
07
0&
#225000
17
b10100 ,
b10011 .
b10011 /
b10100000000000000000000000010011 (
b10100000000000000000000000010011 4
b10011 %
b10011 2
1&
#230000
b10100 +
07
0&
#235000
17
b10101 ,
b10100 .
b10100 /
b10100000000000000000000000010100 (
b10100000000000000000000000010100 4
b10100 %
b10100 2
1&
#240000
b10101 +
07
0&
#245000
17
b10110 ,
b10101 .
b10101 /
b10100000000000000000000000010101 (
b10100000000000000000000000010101 4
b10101 %
b10101 2
1&
#250000
b10110 +
07
0&
#255000
17
b10111 ,
b10110 .
b10110 /
b10100000000000000000000000010110 (
b10100000000000000000000000010110 4
b10110 %
b10110 2
1&
#260000
b10111 +
07
0&
#265000
17
b11000 ,
b10111 .
b10111 /
b10100000000000000000000000010111 (
b10100000000000000000000000010111 4
b10111 %
b10111 2
1&
#270000
b11000 +
07
0&
#275000
17
b11001 ,
b11000 .
b11000 /
b10100000000000000000000000011000 (
b10100000000000000000000000011000 4
b11000 %
b11000 2
1&
#280000
b11001 +
07
0&
#285000
17
b11010 ,
b11001 .
b11001 /
b10100000000000000000000000011001 (
b10100000000000000000000000011001 4
b11001 %
b11001 2
1&
#290000
b11010 +
07
0&
#295000
17
b11011 ,
b11010 .
b11010 /
b10100000000000000000000000011010 (
b10100000000000000000000000011010 4
b11010 %
b11010 2
1&
#300000
b11011 +
07
0&
#305000
17
b11100 ,
b11011 .
b11011 /
b10100000000000000000000000011011 (
b10100000000000000000000000011011 4
b11011 %
b11011 2
1&
#310000
b11100 +
07
0&
#315000
17
b11101 ,
b11100 .
b11100 /
b10100000000000000000000000011100 (
b10100000000000000000000000011100 4
b11100 %
b11100 2
1&
#320000
b11101 +
07
0&
#325000
17
b11110 ,
b11101 .
b11101 /
b10100000000000000000000000011101 (
b10100000000000000000000000011101 4
b11101 %
b11101 2
1&
#330000
b11110 +
07
0&
#335000
17
b11111 ,
b11110 .
b11110 /
b10100000000000000000000000011110 (
b10100000000000000000000000011110 4
b11110 %
b11110 2
1&
#340000
b11111 +
07
0&
#345000
17
b100000 ,
b11111 .
b11111 /
b10100000000000000000000000011111 (
b10100000000000000000000000011111 4
b11111 %
b11111 2
1&
#350000
b100000 +
07
0&
#355000
b100001 +
0:
b10100000000000000000000000000001 "
b10100000000000000000000000000001 6
03
07
b1 #
b1 0
b1 ,
b1 -
b100000 .
0)
1&
#360000
0&
#365000
b10100000000000000000000000000010 "
b10100000000000000000000000000010 6
b10 #
b10 0
b10 ,
b100001 .
b10 -
1&
#370000
0&
#375000
b10100000000000000000000000000011 "
b10100000000000000000000000000011 6
b11 #
b11 0
b11 ,
b100010 .
b11 -
1&
#380000
0&
#385000
b10100000000000000000000000000100 "
b10100000000000000000000000000100 6
b100 #
b100 0
b100 ,
b100011 .
b100 -
1&
#390000
0&
#395000
b10100000000000000000000000000101 "
b10100000000000000000000000000101 6
b101 #
b101 0
b101 ,
b100100 .
b101 -
1&
#400000
0&
#405000
b10100000000000000000000000000110 "
b10100000000000000000000000000110 6
b110 #
b110 0
b110 ,
b100101 .
b110 -
1&
#410000
0&
#415000
b10100000000000000000000000000111 "
b10100000000000000000000000000111 6
b111 #
b111 0
b111 ,
b100110 .
b111 -
1&
#420000
0&
#425000
b10100000000000000000000000001000 "
b10100000000000000000000000001000 6
b1000 #
b1000 0
b1000 ,
b100111 .
b1000 -
1&
#430000
0&
#435000
b10100000000000000000000000001001 "
b10100000000000000000000000001001 6
b1001 #
b1001 0
b1001 ,
b101000 .
b1001 -
1&
#440000
0&
#445000
b10100000000000000000000000001010 "
b10100000000000000000000000001010 6
b1010 #
b1010 0
b1010 ,
b101001 .
b1010 -
1&
#450000
0&
#455000
b10100000000000000000000000001011 "
b10100000000000000000000000001011 6
b1011 #
b1011 0
b1011 ,
b101010 .
b1011 -
1&
#460000
0&
#465000
b10100000000000000000000000001100 "
b10100000000000000000000000001100 6
b1100 #
b1100 0
b1100 ,
b101011 .
b1100 -
1&
#470000
0&
#475000
b10100000000000000000000000001101 "
b10100000000000000000000000001101 6
b1101 #
b1101 0
b1101 ,
b101100 .
b1101 -
1&
#480000
0&
#485000
b10100000000000000000000000001110 "
b10100000000000000000000000001110 6
b1110 #
b1110 0
b1110 ,
b101101 .
b1110 -
1&
#490000
0&
#495000
b10100000000000000000000000001111 "
b10100000000000000000000000001111 6
b1111 #
b1111 0
b1111 ,
b101110 .
b1111 -
1&
#500000
0&
#505000
b10100000000000000000000000010000 "
b10100000000000000000000000010000 6
b10000 #
b10000 0
b10000 ,
b101111 .
b10000 -
1&
#510000
0&
#515000
b10100000000000000000000000010001 "
b10100000000000000000000000010001 6
b10001 #
b10001 0
b10001 ,
b110000 .
b10001 -
1&
#520000
0&
#525000
b10100000000000000000000000010010 "
b10100000000000000000000000010010 6
b10010 #
b10010 0
b10010 ,
b110001 .
b10010 -
1&
#530000
0&
#535000
b10100000000000000000000000010011 "
b10100000000000000000000000010011 6
b10011 #
b10011 0
b10011 ,
b110010 .
b10011 -
1&
#540000
0&
#545000
b10100000000000000000000000010100 "
b10100000000000000000000000010100 6
b10100 #
b10100 0
b10100 ,
b110011 .
b10100 -
1&
#550000
0&
#555000
b10100000000000000000000000010101 "
b10100000000000000000000000010101 6
b10101 #
b10101 0
b10101 ,
b110100 .
b10101 -
1&
#560000
0&
#565000
b10100000000000000000000000010110 "
b10100000000000000000000000010110 6
b10110 #
b10110 0
b10110 ,
b110101 .
b10110 -
1&
#570000
0&
#575000
b10100000000000000000000000010111 "
b10100000000000000000000000010111 6
b10111 #
b10111 0
b10111 ,
b110110 .
b10111 -
1&
#580000
0&
#585000
b10100000000000000000000000011000 "
b10100000000000000000000000011000 6
b11000 #
b11000 0
b11000 ,
b110111 .
b11000 -
1&
#590000
0&
#595000
b10100000000000000000000000011001 "
b10100000000000000000000000011001 6
b11001 #
b11001 0
b11001 ,
b111000 .
b11001 -
1&
#600000
0&
#605000
b10100000000000000000000000011010 "
b10100000000000000000000000011010 6
b11010 #
b11010 0
b11010 ,
b111001 .
b11010 -
1&
#610000
0&
#615000
b10100000000000000000000000011011 "
b10100000000000000000000000011011 6
b11011 #
b11011 0
b11011 ,
b111010 .
b11011 -
1&
#620000
0&
#625000
b10100000000000000000000000011100 "
b10100000000000000000000000011100 6
b11100 #
b11100 0
b11100 ,
b111011 .
b11100 -
1&
#630000
0&
#635000
b10100000000000000000000000011101 "
b10100000000000000000000000011101 6
b11101 #
b11101 0
b11101 ,
b111100 .
b11101 -
1&
#640000
0&
#645000
b10100000000000000000000000011110 "
b10100000000000000000000000011110 6
b11110 #
b11110 0
b11110 ,
b111101 .
b11110 -
1&
#650000
0&
#655000
b10100000000000000000000000011111 "
b10100000000000000000000000011111 6
b11111 #
b11111 0
b11111 ,
b111110 .
b11111 -
1&
#660000
0&
#665000
b1 ,
b111111 .
b100000 -
1&
#670000
0&
#675000
17
1:
13
b1000000 .
b100000 /
b11011110101011010000000000000001 (
b11011110101011010000000000000001 4
b1 %
b1 2
1)
1&
#680000
b100010 +
07
0&
#685000
b100011 +
0:
b11011110101011010000000000000001 "
b11011110101011010000000000000001 6
03
07
b1 #
b1 0
0)
1&
#686000
b10 ,
b1000001 .
b100001 -
#690000
0&
#695000
17
1:
13
b1000010 .
b100001 /
b11011110101011010000000000000010 (
b11011110101011010000000000000010 4
b10 %
b10 2
1)
1&
#700000
b100100 +
07
0&
#705000
b100101 +
0:
b11011110101011010000000000000010 "
b11011110101011010000000000000010 6
03
07
b10 #
b10 0
0)
1&
#706000
b11 ,
b1000011 .
b100010 -
#710000
0&
#715000
17
1:
13
b1000100 .
b100010 /
b11011110101011010000000000000011 (
b11011110101011010000000000000011 4
b11 %
b11 2
1)
1&
#720000
b100110 +
07
0&
#725000
b100111 +
0:
b11011110101011010000000000000011 "
b11011110101011010000000000000011 6
03
07
b11 #
b11 0
0)
1&
#726000
b100 ,
b1000101 .
b100011 -
#730000
0&
#735000
17
1:
13
b1000110 .
b100011 /
b11011110101011010000000000000100 (
b11011110101011010000000000000100 4
b100 %
b100 2
1)
1&
#740000
b101000 +
07
0&
#745000
b101001 +
0:
b11011110101011010000000000000100 "
b11011110101011010000000000000100 6
03
07
b100 #
b100 0
0)
1&
#746000
b101 ,
b1000111 .
b100100 -
#750000
0&
#755000
17
1:
13
b1001000 .
b100100 /
b11011110101011010000000000000101 (
b11011110101011010000000000000101 4
b101 %
b101 2
1)
1&
#760000
b101010 +
07
0&
#765000
b101011 +
0:
b11011110101011010000000000000101 "
b11011110101011010000000000000101 6
03
07
b101 #
b101 0
0)
1&
#766000
b110 ,
b1001001 .
b100101 -
#770000
0&
#775000
17
1:
13
b1001010 .
b100101 /
b11011110101011010000000000000110 (
b11011110101011010000000000000110 4
b110 %
b110 2
1)
1&
#780000
b101100 +
07
0&
#785000
b101101 +
0:
b11011110101011010000000000000110 "
b11011110101011010000000000000110 6
03
07
b110 #
b110 0
0)
1&
#786000
b111 ,
b1001011 .
b100110 -
#790000
0&
#795000
17
1:
13
b1001100 .
b100110 /
b11011110101011010000000000000111 (
b11011110101011010000000000000111 4
b111 %
b111 2
1)
1&
#800000
b101110 +
07
0&
#805000
b101111 +
0:
b11011110101011010000000000000111 "
b11011110101011010000000000000111 6
03
07
b111 #
b111 0
0)
1&
#806000
b1000 ,
b1001101 .
b100111 -
#810000
0&
#815000
17
1:
13
b1001110 .
b100111 /
b11011110101011010000000000001000 (
b11011110101011010000000000001000 4
b1000 %
b1000 2
1)
1&
#820000
b110000 +
07
0&
#825000
b110001 +
0:
b11011110101011010000000000001000 "
b11011110101011010000000000001000 6
03
07
b1000 #
b1000 0
0)
1&
#826000
b1001 ,
b1001111 .
b101000 -
#830000
0&
#835000
17
1:
13
b1010000 .
b101000 /
b11011110101011010000000000001001 (
b11011110101011010000000000001001 4
b1001 %
b1001 2
1)
1&
#840000
b110010 +
07
0&
#845000
b110011 +
0:
b11011110101011010000000000001001 "
b11011110101011010000000000001001 6
03
07
b1001 #
b1001 0
0)
1&
#846000
b1010 ,
b1010001 .
b101001 -
#850000
0&
#855000
17
1:
13
b1010010 .
b101001 /
b11011110101011010000000000001010 (
b11011110101011010000000000001010 4
b1010 %
b1010 2
1)
1&
#860000
b110100 +
07
0&
#865000
b110101 +
0:
b11011110101011010000000000001010 "
b11011110101011010000000000001010 6
03
07
b1010 #
b1010 0
0)
1&
#866000
b1011 ,
b1010011 .
b101010 -
#870000
0&
#875000
17
1:
13
b1010100 .
b101010 /
b11011110101011010000000000001011 (
b11011110101011010000000000001011 4
b1011 %
b1011 2
1)
1&
#880000
b110110 +
07
0&
#885000
b110111 +
0:
b11011110101011010000000000001011 "
b11011110101011010000000000001011 6
03
07
b1011 #
b1011 0
0)
1&
#886000
b1100 ,
b1010101 .
b101011 -
#890000
0&
#895000
17
1:
13
b1010110 .
b101011 /
b11011110101011010000000000001100 (
b11011110101011010000000000001100 4
b1100 %
b1100 2
1)
1&
#900000
b111000 +
07
0&
#905000
b111001 +
0:
b11011110101011010000000000001100 "
b11011110101011010000000000001100 6
03
07
b1100 #
b1100 0
0)
1&
#906000
b1101 ,
b1010111 .
b101100 -
#910000
0&
#915000
17
1:
13
b1011000 .
b101100 /
b11011110101011010000000000001101 (
b11011110101011010000000000001101 4
b1101 %
b1101 2
1)
1&
#920000
b111010 +
07
0&
#925000
b111011 +
0:
b11011110101011010000000000001101 "
b11011110101011010000000000001101 6
03
07
b1101 #
b1101 0
0)
1&
#926000
b1110 ,
b1011001 .
b101101 -
#930000
0&
#935000
17
1:
13
b1011010 .
b101101 /
b11011110101011010000000000001110 (
b11011110101011010000000000001110 4
b1110 %
b1110 2
1)
1&
#940000
b111100 +
07
0&
#945000
b111101 +
0:
b11011110101011010000000000001110 "
b11011110101011010000000000001110 6
03
07
b1110 #
b1110 0
0)
1&
#946000
b1111 ,
b1011011 .
b101110 -
#950000
0&
#955000
17
1:
13
b1011100 .
b101110 /
b11011110101011010000000000001111 (
b11011110101011010000000000001111 4
b1111 %
b1111 2
1)
1&
#960000
b111110 +
07
0&
#965000
b111111 +
0:
b11011110101011010000000000001111 "
b11011110101011010000000000001111 6
03
07
b1111 #
b1111 0
0)
1&
#966000
b11011110101011010000000000000010 !
b11011110101011010000000000000010 5
b11011110101011010000000000000001 "
b11011110101011010000000000000001 6
b10 $
b10 1
b1 #
b1 0
b10000 ,
b1011101 .
b101111 -
#970000
0&
#975000
b1011110 .
b110000 -
1&
#980000
0&
#985000
b1011111 .
b110001 -
1&
#990000
0&
#995000
b1100000 .
b110010 -
1&
#1000000
0&
#1005000
b1100001 .
b110011 -
1&
#1010000
0&
#1015000
b1100010 .
b110100 -
1&
#1020000
0&
#1025000
b1100011 .
b110101 -
1&
#1030000
0&
#1035000
b1100100 .
b110110 -
1&
#1040000
0&
#1045000
b1100101 .
b110111 -
1&
#1050000
0&
#1055000
b1100110 .
b111000 -
1&
#1060000
0&
#1065000
b1100111 .
b111001 -
1&
#1070000
0&
#1075000
b1101000 .
b111010 -
1&
#1080000
0&
#1085000
b1101001 .
b111011 -
1&
#1090000
0&
#1095000
b1101010 .
b111100 -
1&
#1100000
0&
#1105000
b1101011 .
b111101 -
1&
#1110000
0&
#1115000
b1101100 .
b111110 -
1&
#1120000
0&
#1125000
b1101101 .
b111111 -
1&
#1130000
0&
#1135000
b1101110 .
b1000000 -
1&
#1140000
0&
#1145000
b1101111 .
b1000001 -
1&
#1150000
0&
#1155000
b1110000 .
b1000010 -
1&
#1160000
0&
#1165000
b1110001 .
b1000011 -
1&
#1170000
0&
#1175000
b1110010 .
b1000100 -
1&
#1180000
0&
#1185000
b1110011 .
b1000101 -
1&
#1190000
0&
#1195000
b1110100 .
b1000110 -
1&
#1200000
0&
#1205000
b1110101 .
b1000111 -
1&
#1210000
0&
#1215000
b1110110 .
b1001000 -
1&
#1220000
0&
#1225000
b1110111 .
b1001001 -
1&
#1230000
0&
#1235000
b1111000 .
b1001010 -
1&
#1240000
0&
#1245000
b1111001 .
b1001011 -
1&
#1250000
0&
#1255000
b1111010 .
b1001100 -
1&
#1260000
0&
#1265000
b1111011 .
b1001101 -
1&
#1270000
0&
#1275000
b1111100 .
b1001110 -
1&
#1280000
0&
#1285000
b1111101 .
b1001111 -
1&
#1290000
0&
#1295000
b1111110 .
b1010000 -
1&
#1300000
0&
#1305000
b1111111 .
b1010001 -
1&
#1310000
0&
#1315000
b10000000 .
b1010010 -
1&
#1320000
0&
#1325000
b10000001 .
b1010011 -
1&
#1330000
0&
#1335000
b10000010 .
b1010100 -
1&
#1340000
0&
#1345000
b10000011 .
b1010101 -
1&
#1350000
0&
#1355000
b10000100 .
b1010110 -
1&
#1360000
0&
#1365000
b10000101 .
b1010111 -
1&
#1370000
0&
#1375000
b10000110 .
b1011000 -
1&
#1380000
0&
#1385000
b10000111 .
b1011001 -
1&
#1390000
0&
#1395000
b10001000 .
b1011010 -
1&
#1400000
0&
#1405000
b10001001 .
b1011011 -
1&
#1410000
0&
#1415000
b10001010 .
b1011100 -
1&
#1420000
0&
#1425000
b10001011 .
b1011101 -
1&
#1430000
0&
#1435000
b10001100 .
b1011110 -
1&
#1440000
0&
#1445000
b10001101 .
b1011111 -
1&
#1450000
0&
#1455000
b10001110 .
b1100000 -
1&
#1460000
0&
#1465000
b10001111 .
b1100001 -
1&
