sim/v006_auipc_fixed/alu_wally.v
///////////////////////////////////////////
// alu_wally.v — Simplified Wally ALU for operand isolation testing
//
// Faithfully reproduces the core operations from cvw/src/ieu/alu.sv:
//   - ADD/SUB (ALUSelect=000)
//   - SLL/SRL/SRA (ALUSelect=001)
//   - SLT (ALUSelect=010)
//   - SLTU (ALUSelect=011)
//   - XOR (ALUSelect=100)
//   - OR (ALUSelect=110)
//   - AND (ALUSelect=111)
//
// Omits BMU extensions (ZBA/ZBB/ZBC/ZBS) since they're irrelevant
// to demonstrating operand isolation.
///////////////////////////////////////////

module alu_wally #(
  parameter XLEN = 32
) (
  input  wire [XLEN-1:0] A, B,
  input  wire             SubArith,   // 1 = subtract / arithmetic shift
  input  wire [2:0]       ALUSelect,  // Operation select
  output reg  [XLEN-1:0]  ALUResult,
  output wire [XLEN-1:0]  Sum
);

  wire [XLEN-1:0] CondInvB = SubArith ? ~B : B;
  wire             Carry;

  // Adder
  assign {Carry, Sum} = A + CondInvB + {{(XLEN-1){1'b0}}, SubArith};

  // Shift
  wire [XLEN-1:0] ShiftLeft  = A << B[4:0];
  wire [XLEN-1:0] ShiftRight = SubArith ?
    ($signed(A) >>> B[4:0]) : (A >> B[4:0]);

  // Comparisons
  wire Neg  = Sum[XLEN-1];
  wire Asign = A[XLEN-1];
  wire Bsign = B[XLEN-1];
  wire LT  = (Asign & ~Bsign) | (Asign & Neg) | (~Bsign & Neg);
  wire LTU = ~Carry;

  // Result mux
  always @(*) begin
    case (ALUSelect)
      3'b000: ALUResult = Sum;
      3'b001: ALUResult = ALUSelect[2] ? ShiftRight : ShiftLeft;  // simplified
      3'b010: ALUResult = {{(XLEN-1){1'b0}}, LT};
      3'b011: ALUResult = {{(XLEN-1){1'b0}}, LTU};
      3'b100: ALUResult = A ^ CondInvB;
      3'b101: ALUResult = ShiftRight;
      3'b110: ALUResult = A | CondInvB;
      3'b111: ALUResult = A & CondInvB;
    endcase
  end

endmodule

sim/v006_auipc_fixed/alu_isolated.v
///////////////////////////////////////////
// alu_isolated.v — ALU with AND-clamping operand isolation
//
// When alu_active=0, inputs A and B are clamped to zero.
// This prevents random toggle propagation through the combinational
// cloud (adder, shifter, comparators) when the ALU result is unused
// (e.g., during LOAD, STORE, NOP, BRANCH instructions).
///////////////////////////////////////////

module alu_isolated #(
  parameter XLEN = 32
) (
  input  wire [XLEN-1:0] A, B,
  input  wire             SubArith,
  input  wire [2:0]       ALUSelect,
  input  wire             alu_active,  // NEW: 1 when ALU result is needed
  output wire [XLEN-1:0]  ALUResult,
  output wire [XLEN-1:0]  Sum
);

  // Operand isolation: AND-clamp inputs when not active
  wire [XLEN-1:0] A_clamped = A & {XLEN{alu_active}};
  wire [XLEN-1:0] B_clamped = B & {XLEN{alu_active}};

  // Instantiate the actual ALU with clamped inputs
  alu_wally #(.XLEN(XLEN)) core_alu (
    .A(A_clamped),
    .B(B_clamped),
    .SubArith(SubArith & alu_active),
    .ALUSelect(ALUSelect),
    .ALUResult(ALUResult),
    .Sum(Sum)
  );

endmodule

sim/v004_isolation/tb_alu.v
///////////////////////////////////////////
// tb_alu.v — Testbench for ALU Operand Isolation
//
// Tests functional equivalence of baseline vs isolated ALU.
// Counts toggle events inside the ALU combinational logic to prove
// dynamic power reduction during inactive cycles.
///////////////////////////////////////////
`timescale 1ns/1ps

module tb_alu;

  parameter XLEN = 32;

  reg [XLEN-1:0] A, B;
  reg            SubArith;
  reg [2:0]      ALUSelect;
  reg            alu_active;

  wire [XLEN-1:0] ALUResult_base, Sum_base;
  wire [XLEN-1:0] ALUResult_iso, Sum_iso;

  // Baseline ALU (always sees toggling inputs)
  alu_wally #(.XLEN(XLEN)) dut_base (
    .A(A), .B(B), .SubArith(SubArith), .ALUSelect(ALUSelect),
    .ALUResult(ALUResult_base), .Sum(Sum_base)
  );

  // Isolated ALU (inputs clamped to 0 when inactive)
  alu_isolated #(.XLEN(XLEN)) dut_iso (
    .A(A), .B(B), .SubArith(SubArith), .ALUSelect(ALUSelect),
    .alu_active(alu_active),
    .ALUResult(ALUResult_iso), .Sum(Sum_iso)
  );

  integer i, errors;
  integer active_cycles, inactive_cycles;

  // We want to count toggles in the internal Sum output (representing adder logic)
  integer base_adder_toggles, iso_adder_toggles;
  reg [XLEN-1:0] prev_sum_base, prev_sum_iso;

  always @(Sum_base) begin
    if ($time > 0) base_adder_toggles = base_adder_toggles + 1;
  end

  always @(Sum_iso) begin
    if ($time > 0) iso_adder_toggles = iso_adder_toggles + 1;
  end

  initial begin
    $dumpfile("v004_isolation.vcd");
    $dumpvars(0, tb_alu);

    errors = 0;
    active_cycles = 0; inactive_cycles = 0;
    base_adder_toggles = 0; iso_adder_toggles = 0;
    prev_sum_base = 0; prev_sum_iso = 0;

    A = 0; B = 0; SubArith = 0; ALUSelect = 0; alu_active = 0;
    #10;

    $display("========================================");
    $display("v004 ALU OPERAND ISOLATION SIMULATION");
    $display("========================================");

    // TEST 1: Active compute cycles (ALU is used)
    $display("[TEST 1] Active Cycles: ADD, SUB, XOR, AND...");
    alu_active = 1;
    
    // Cycle 1: ADD (A + B)
    A = 32'h0000_1111; B = 32'h0000_2222; SubArith = 0; ALUSelect = 3'b000;
    #10;
    if (ALUResult_base !== ALUResult_iso || ALUResult_iso !== 32'h0000_3333) begin
      $display("  ERROR in ADD: base=%h iso=%h (want 00003333)", ALUResult_base, ALUResult_iso);
      errors = errors + 1;
    end
    active_cycles = active_cycles + 1;

    // Cycle 2: SUB (A - B)
    A = 32'h0000_5555; B = 32'h0000_1111; SubArith = 1; ALUSelect = 3'b000;
    #10;
    if (ALUResult_base !== ALUResult_iso || ALUResult_iso !== 32'h0000_4444) begin
      $display("  ERROR in SUB: base=%h iso=%h (want 00004444)", ALUResult_base, ALUResult_iso);
      errors = errors + 1;
    end
    active_cycles = active_cycles + 1;

    // Cycle 3: XOR
    A = 32'hFFFF_0000; B = 32'h0000_FFFF; SubArith = 0; ALUSelect = 3'b100;
    #10;
    if (ALUResult_base !== ALUResult_iso || ALUResult_iso !== 32'hFFFF_FFFF) begin
      $display("  ERROR in XOR: base=%h iso=%h (want FFFFFFFF)", ALUResult_base, ALUResult_iso);
      errors = errors + 1;
    end
    active_cycles = active_cycles + 1;

    // TEST 2: Inactive cycles (e.g. LOAD, STORE, BRANCH - ALU not needed)
    $display("[TEST 2] Inactive Cycles (Toggle suppression test)...");
    alu_active = 0;
    
    // We will spam random inputs simulating datapath noise while ALU is inactive
    for (i = 0; i < 50; i = i + 1) begin
      A = $random;
      B = $random;
      SubArith = $random % 2;
      ALUSelect = $random % 8;
      #10;
      // In isolated ALU, ALUResult_iso should be computed as if A=0, B=0.
      // E.g. 0 + 0 = 0.
      inactive_cycles = inactive_cycles + 1;
    end

    // TEST 3: Back to active compute
    $display("[TEST 3] Back to Active Compute...");
    alu_active = 1;
    A = 32'h1234_5678; B = 32'h8765_4321; SubArith = 0; ALUSelect = 3'b000;
    #10;
    if (ALUResult_base !== ALUResult_iso) begin
      $display("  ERROR in Wakeup ADD: base=%h iso=%h", ALUResult_base, ALUResult_iso);
      errors = errors + 1;
    end
    active_cycles = active_cycles + 1;

    $display("========================================");
    $display("v004 ISOLATION RESULTS");
    $display("========================================");
    $display("Active cycles:           %0d", active_cycles);
    $display("Inactive cycles:         %0d", inactive_cycles);
    $display("Errors (Equivalence):    %0d", errors);
    $display("----------------------------------------");
    $display("Combinational Toggle Count (Adder cloud):");
    $display("  Baseline ALU toggles: %0d", base_adder_toggles);
    $display("  Isolated ALU toggles: %0d", iso_adder_toggles);
    $display("  Toggle Reduction:     %0d%%", 
      ((base_adder_toggles - iso_adder_toggles) * 100) / base_adder_toggles);
    $display("========================================");
    
    if (errors == 0) $display("STATUS: PASS");
    else $display("STATUS: FAIL");

    $finish;
  end

endmodule

sim/v004_isolation/v004_isolation.vcd
$date
	Tue Jul 21 13:52:49 2026
$end
$version
	Icarus Verilog
$end
$timescale
	1ps
$end
$scope module tb_alu $end
$var wire 32 ! Sum_iso [31:0] $end
$var wire 32 " Sum_base [31:0] $end
$var wire 32 # ALUResult_iso [31:0] $end
$var wire 32 $ ALUResult_base [31:0] $end
$var reg 32 % A [31:0] $end
$var reg 3 & ALUSelect [2:0] $end
$var reg 32 ' B [31:0] $end
$var reg 1 ( SubArith $end
$var reg 1 ) alu_active $end
$var reg 32 * prev_sum_base [31:0] $end
$var reg 32 + prev_sum_iso [31:0] $end
$var integer 32 , active_cycles [31:0] $end
$var integer 32 - base_adder_toggles [31:0] $end
$var integer 32 . errors [31:0] $end
$var integer 32 / i [31:0] $end
$var integer 32 0 inactive_cycles [31:0] $end
$var integer 32 1 iso_adder_toggles [31:0] $end
$scope module dut_base $end
$var wire 32 2 A [31:0] $end
$var wire 3 3 ALUSelect [2:0] $end
$var wire 32 4 B [31:0] $end
$var wire 1 5 LT $end
$var wire 1 6 LTU $end
$var wire 1 ( SubArith $end
$var wire 32 7 Sum [31:0] $end
$var wire 32 8 ShiftRight [31:0] $end
$var wire 32 9 ShiftLeft [31:0] $end
$var wire 1 : Neg $end
$var wire 32 ; CondInvB [31:0] $end
$var wire 1 < Carry $end
$var wire 1 = Bsign $end
$var wire 1 > Asign $end
$var reg 32 ? ALUResult [31:0] $end
$upscope $end
$scope module dut_iso $end
$var wire 32 @ A [31:0] $end
$var wire 3 A ALUSelect [2:0] $end
$var wire 32 B A_clamped [31:0] $end
$var wire 32 C B [31:0] $end
$var wire 32 D B_clamped [31:0] $end
$var wire 1 ( SubArith $end
$var wire 1 ) alu_active $end
$var wire 32 E Sum [31:0] $end
$var wire 32 F ALUResult [31:0] $end
$scope module core_alu $end
$var wire 32 G A [31:0] $end
$var wire 3 H ALUSelect [2:0] $end
$var wire 32 I B [31:0] $end
$var wire 1 J LT $end
$var wire 1 K LTU $end
$var wire 1 L SubArith $end
$var wire 32 M Sum [31:0] $end
$var wire 32 N ShiftRight [31:0] $end
$var wire 32 O ShiftLeft [31:0] $end
$var wire 1 P Neg $end
$var wire 32 Q CondInvB [31:0] $end
$var wire 1 R Carry $end
$var wire 1 S Bsign $end
$var wire 1 T Asign $end
$var reg 32 U ALUResult [31:0] $end
$upscope $end
$upscope $end
$upscope $end
$enddefinitions $end
#0
$dumpvars
b0 U
0T
0S
0R
b0 Q
0P
b0 O
b0 N
b0 M
0L
1K
0J
b0 I
b0 H
b0 G
b0 F
b0 E
b0 D
b0 C
b0 B
b0 A
b0 @
b0 ?
0>
0=
0<
b0 ;
0:
b0 9
b0 8
b0 7
16
05
b0 4
b0 3
b0 2
b0 1
b0 0
bx /
b0 .
b0 -
b0 ,
b0 +
b0 *
0)
0(
b0 '
b0 &
b0 %
b0 $
b0 #
b0 "
b0 !
$end
#10000
b1 1
b11001100110011 #
b11001100110011 F
b11001100110011 U
b10 -
b11001100110011 $
b11001100110011 ?
b11001100110011 !
b11001100110011 E
b11001100110011 M
b10001000100 N
b10001000100010 Q
b10001000100010 ;
b11001100110011 "
b11001100110011 7
b10001000100 8
b100010001000100 O
b1000100010001 B
b1000100010001 G
b10001000100010 D
b10001000100010 I
b10001000100010 '
b10001000100010 4
b10001000100010 C
b100010001000100 9
b1000100010001 %
b1000100010001 2
b1000100010001 @
1)
#20000
0K
06
1R
b100 1
b100010001000100 #
b100010001000100 F
b100010001000100 U
1<
b11111111111111111110111011101110 Q
b101 -
b100010001000100 $
b100010001000100 ?
b100010001000100 !
b100010001000100 E
b100010001000100 M
b0 N
1L
b11111111111111111110111011101110 ;
b1000100010001 D
b1000100010001 I
b100010001000100 "
b100010001000100 7
b0 8
b10101010101010100000000000000000 O
b101010101010101 B
b101010101010101 G
1(
b1000100010001 '
b1000100010001 4
b1000100010001 C
b10101010101010100000000000000000 9
b101010101010101 %
b101010101010101 2
b101010101010101 @
b1 ,
#30000
1J
1K
15
16
0R
1P
b110 1
0<
b1111111111111111 Q
1:
b111 -
b11111111111111111111111111111111 !
b11111111111111111111111111111111 E
b11111111111111111111111111111111 M
b1 N
1T
b11111111111111111111111111111111 #
b11111111111111111111111111111111 F
b11111111111111111111111111111111 U
b1111111111111111 ;
0L
b1111111111111111 D
b1111111111111111 I
b11111111111111111111111111111111 "
b11111111111111111111111111111111 7
b11111111111111111111111111111111 $
b11111111111111111111111111111111 ?
b1 8
1>
b0 O
b11111111111111110000000000000000 B
b11111111111111110000000000000000 G
b100 &
b100 3
b100 A
b100 H
0(
b1111111111111111 '
b1111111111111111 4
b1111111111111111 C
b0 9
b11111111111111110000000000000000 %
b11111111111111110000000000000000 2
b11111111111111110000000000000000 @
b10 ,
#40000
0J
05
16
0P
b111 1
0<
0:
b1010 -
b0 !
b0 E
b0 M
b0 N
0T
b0 Q
b1 #
b1 F
b1 U
b111111011101101010000101111110 ;
b100100001010100110101001001000 9
1=
b1 $
b1 ?
b1010001100010111101011010100011 "
b1010001100010111101011010100011 7
b1001000010101001101010010010 8
0>
b0 B
b0 G
b0 D
b0 I
b11 &
b11 3
b11 A
b11 H
1(
b11000000100010010101111010000001 '
b11000000100010010101111010000001 4
b11000000100010010101111010000001 C
b10010000101010011010100100100 %
b10010000101010011010100100100 2
b10010000101010011010100100100 @
b0 /
0)
b11 ,
#50000
15
1:
b10111001001000000110011001110010 ;
b1100 -
b0 #
b0 F
b0 U
0=
b10111111110110011110000110000000 "
b10111111110110011110000110000000 7
b1 $
b1 ?
b11010111001011 8
b10 &
b10 3
b10 A
b10 H
b1000110110111111001100110001101 '
b1000110110111111001100110001101 4
b1000110110111111001100110001101 C
b101111011000011010000000000000 9
b110101110010111101100001101 %
b110101110010111101100001101 2
b110101110010111101100001101 @
b1 /
b1 0
#60000
05
0:
b1110 -
b110110101111100110100001101 ;
b111110010111011000000001110 "
b111110010111011000000001110 7
b11110011111 $
b11110011111 ?
b11110011111 8
b101 &
b101 3
b101 A
b101 H
0(
b110110101111100110100001101 '
b110110101111100110100001101 4
b110110101111100110100001101 C
b1111100011000000010000000000000 9
b111100111110001100000001 %
b111100111110001100000001 2
b111100111110001100000001 @
b10 /
b10 0
#70000
06
1<
b10001 -
b10111001110100100000100001110011 ;
b110000101001100110000001100001 "
b110000101001100110000001100001 7
b11111111110101100101111111111111 $
b11111111110101100101111111111111 ?
b1110110110101000101 8
b110 &
b110 3
b110 A
b110 H
1(
b1000110001011011111011110001100 '
b1000110001011011111011110001100 4
b1000110001011011111011110001100 C
b1000101011111101101000000000000 9
b1110110110101000101011111101101 %
b1110110110101000101011111101101 2
b1110110110101000101011111101101 @
b11 /
b11 0
#80000
05
b101010111011000010110101010101 ;
0:
b10011 -
1=
b1101111000111011001000011011 "
b1101111000111011001000011011 7
b100010111001000000010001000101 $
b100010111001000000010001000101 ?
b1110001011110111100001 8
1>
b111 &
b111 3
b111 A
b111 H
b11010101000100111101001010101010 '
b11010101000100111101001010101010 4
b11010101000100111101001010101010 C
b11011110000100110001010000000000 9
b11100010111101111000010011000101 %
b11100010111101111000010011000101 2
b11100010111101111000010011000101 @
b100 /
b100 0
#90000
15
1:
b10101 -
16
b1000111111011001101101110001111 ;
0=
b11010001000111111011000110100001 "
b11010001000111111011000110100001 7
0<
b11001111111111101101111110011111 $
b11001111111111101101111110011111 ?
b10001001001100101 8
b110 &
b110 3
b110 A
b110 H
0(
b1000111111011001101101110001111 '
b1000111111011001101101110001111 4
b1000111111011001101101110001111 C
b1101011000010010000000000000000 9
b10001001001100101101011000010010 %
b10001001001100101101011000010010 2
b10001001001100101101011000010010 @
b101 /
b101 0
#100000
15
1:
b10111 -
06
b11100010110010100100111011000101 ;
1=
b11010110110010101100100110101101 "
b11010110110010101100100110101101 7
1<
b111101000000000001111010111 $
b111101000000000001111010111 ?
b111101000000000001111010111 8
b101 &
b101 3
b101 A
b101 H
b11100010110010100100111011000101 '
b11100010110010100100111011000101 4
b11100010110010100100111011000101 C
b10000000000011110101110100000000 9
b11110100000000000111101011101000 %
b11110100000000000111101011101000 2
b11110100000000000111101011101000 @
b110 /
b110 0
#110000
15
16
0<
1:
b11010 -
b1001101010110001101100110011010 ;
b11100100000001000011000111001000 "
b11100100000001000011000111001000 7
b1 $
b1 ?
b100101101010101101011000001 8
b10 &
b10 3
b10 A
b10 H
1(
b10110010101001110010011001100101 '
b10110010101001110010011001100101 4
b10110010101001110010011001100101 C
b11010101011010110000010110100000 9
b10010110101010110101100000101101 %
b10010110101010110101100000101101 2
b10010110101010110101100000101101 @
b111 /
b111 0
#120000
1:
b11100 -
16
b10000011001000010000100100000 ;
0=
b11010000100111110100001110100000 "
b11010000100111110100001110100000 7
0<
b11000000001110110010001010000000 $
b11000000001110110010001010000000 ?
b11000000001110110010001010000000 8
b101 &
b101 3
b101 A
b101 H
0(
b10000011001000010000100100000 '
b10000011001000010000100100000 4
b10000011001000010000100100000 C
b11000000001110110010001010000000 9
b11000000001110110010001010000000 %
b11000000001110110010001010000000 2
b11000000001110110010001010000000 @
b1000 /
b1000 0
#130000
05
0:
06
1<
b11111 -
b1 #
b1 F
b1 U
b1110110011111000100011111101100 ;
1=
b1000001100111001000011010000011 "
b1000001100111001000011010000011 7
b0 $
b0 ?
b1100101100100 8
b11 &
b11 3
b11 A
b11 H
1(
b10001001100000111011100000010011 '
b10001001100000111011100000010011 4
b10001001100000111011100000010011 C
b11110100101100000000000000000000 9
b11001011001000000011111010010110 %
b11001011001000000011111010010110 2
b11001011001000000011111010010110 @
b1001 /
b1001 0
#140000
0:
b100001 -
06
b0 #
b0 F
b0 U
b11101010101001100010101011010101 ;
b100000010001100000100001000000 "
b100000010001100000100001000000 7
1<
b11111111101111111111111111111111 $
b11111111101111111111111111111111 ?
b110101100 8
0>
b110 &
b110 3
b110 A
b110 H
0(
b11101010101001100010101011010101 '
b11101010101001100010101011010101 4
b11101010101001100010101011010101 C
b10101101011000000000000000000000 9
b110101100111111101110101101011 %
b110101100111111101110101101011 2
b110101100111111101110101101011 @
b1010 /
b1010 0
#150000
0:
b100100 -
16
b11000001110101000110100110000 ;
b100111001110100111011001001110 "
b100111001110100111011001001110 7
0<
b0 $
b0 ?
b1110111111111 8
b10 &
b10 3
b10 A
b10 H
1(
b11100111110001010111001011001111 '
b11100111110001010111001011001111 4
b11100111110001010111001011001111 C
b11110100100011101000000000000000 9
b1110111111111110100100011101 %
b1110111111111110100100011101 2
b1110111111111110100100011101 @
b1011 /
b1011 0
#160000
b1 $
b1 ?
15
06
1<
1:
b100110 -
b10011110001100010100110000111100 ;
b10000011101001000101011100000110 "
b10000011101001000101011100000110 7
b1110 8
1>
0(
b10011110001100010100110000111100 '
b10011110001100010100110000111100 4
b10011110001100010100110000111100 C
b10100000000000000000000000000000 9
b11100101011100110000101011001010 %
b11100101011100110000101011001010 2
b11100101011100110000101011001010 @
b1100 /
b1100 0
#170000
05
0:
b101000 -
06
b11101100010010110011010011011000 ;
b1101000011111110100000011001 "
b1101000011111110100000011001 7
1<
b1000001000000000000000000000000 $
b1000001000000000000000000000000 ?
b100000 8
0>
b1 &
b1 3
b1 A
b1 H
b11101100010010110011010011011000 '
b11101100010010110011010011011000 4
b11101100010010110011010011011000 C
b1000001000000000000000000000000 9
b100000110001001011001101000001 %
b100000110001001011001101000001 2
b100000110001001011001101000001 @
b1101 /
b1101 0
#180000
15
1:
16
0<
b101010 -
b1011011000000100110010110110110 ;
0=
b11010000110001110111001110100001 "
b11010000110001110111001110100001 7
b1111111110001110110110111111111 $
b1111111110001110110110111111111 ?
b111010111 8
b110 &
b110 3
b110 A
b110 H
b1011011000000100110010110110110 '
b1011011000000100110010110110110 4
b1011011000000100110010110110110 C
b1111010110000000000000000000000 9
b1110101110001010000110111101011 %
b1110101110001010000110111101011 2
b1110101110001010000110111101011 @
b1110 /
b1110 0
#190000
1:
b101101 -
06
b11101010111100000010001011010101 ;
b11001001011001010010010110010010 "
b11001001011001010010010110010010 7
1<
b11010100000010101111000000000000 $
b11010100000010101111000000000000 ?
b1101111001110101000000 8
1>
b1 &
b1 3
b1 A
b1 H
1(
b10101000011111101110100101010 '
b10101000011111101110100101010 4
b10101000011111101110100101010 C
b11010100000010101111000000000000 9
b11011110011101010000001010111100 %
b11011110011101010000001010111100 2
b11011110011101010000001010111100 @
b1111 /
b1111 0
#200000
05
b11011000000011011010101010110000 ;
0:
b101111 -
b11010111111111110110000110110 "
b11010111111111110110000110110 7
b0 $
b0 ?
b1000010111100100 8
0>
b10 &
b10 3
b10 A
b10 H
b100111111100100101010101001111 '
b100111111100100101010101001111 4
b100111111100100101010101001111 C
b100000110000101000000000000000 9
b1000010111100100100000110000101 %
b1000010111100100100000110000101 2
b1000010111100100100000110000101 @
b10000 /
b10000 0
#210000
15
b11110101010101011011010011101010 ;
1:
b110001 -
b10110100011110001110011101101001 "
b10110100011110001110011101101001 7
b1001111110000000000000000000000 $
b1001111110000000000000000000000 ?
b10111111001 8
1>
b1 &
b1 3
b1 A
b1 H
b1010101010100100101100010101 '
b1010101010100100101100010101 4
b1010101010100100101100010101 C
b1001111110000000000000000000000 9
b10111111001000110011001001111110 %
b10111111001000110011001001111110 2
b10111111001000110011001001111110 @
b10001 /
b10001 0
#220000
05
b11011001110010100000010010110011 ;
0:
b110011 -
b1010111011010000110000010110 "
b1010111011010000110000010110 7
b10001000000100000010000100010 $
b10001000000100000010000100010 ?
b110001001000110000 8
0>
b111 &
b111 3
b111 A
b111 H
b100110001101011111101101001100 '
b100110001101011111101101001100 4
b100110001101011111101101001100 C
b110000011101100010000000000000 9
b110001001000110000011101100010 %
b110001001000110000011101100010 2
b110001001000110000011101100010 @
b10010 /
b10010 0
#230000
1:
16
0<
b100100001100101001111101001000 ;
b110101 -
1=
b10100000101000000100100101000001 "
b10100000101000000100100101000001 7
b1011000010111110011011010110000 $
b1011000010111110011011010110000 ?
b11111000 8
b100 &
b100 3
b100 A
b100 H
b11011011110011010110000010110111 '
b11011011110011010110000010110111 4
b11011011110011010110000010110111 C
b11111100000000000000000000000000 9
b1111100011011011010100111111000 %
b1111100011011011010100111111000 2
b1111100011011011010100111111000 @
b10011 /
b10011 0
#240000
0:
06
15
1<
b10111011001000011100100001110110 ;
b110111 -
0=
b1101000111011011000100011010010 "
b1101000111011011000100011010010 7
b1101000111011011000100011010010 $
b1101000111011011000100011010010 ?
b10101101110010111100000 8
1>
b0 &
b0 3
b0 A
b0 H
b1000100110111100011011110001001 '
b1000100110111100011011110001001 4
b1000100110111100011011110001001 C
b10010111100000001011011000000000 9
b10101101110010111100000001011011 %
b10101101110010111100000001011011 2
b10101101110010111100000001011011 @
b10100 /
b10100 0
#250000
1:
b111001 -
b10101000110001111111110001010001 ;
1=
b10010100110001101011110100101000 "
b10010100110001101011110100101000 7
b1000011001110010011110010000110 $
b1000011001110010011110010000110 ?
b111010111111111 8
b100 &
b100 3
b100 A
b100 H
0(
b10101000110001111111110001010001 '
b10101000110001111111110001010001 4
b10101000110001111111110001010001 C
b10000001101011100000000000000000 9
b11101011111111101100000011010111 %
b11101011111111101100000011010111 2
b11101011111111101100000011010111 @
b10101 /
b10101 0
#260000
0:
b111100 -
b10011011101010000001001000110111 ;
0=
b1111100110101001110000011111010 "
b1111100110101001110000011111010 7
b111000010010110011001110 $
b111000010010110011001110 ?
b111000010010110011001110 8
b101 &
b101 3
b101 A
b101 H
1(
b1100100010101111110110111001000 '
b1100100010101111110110111001000 4
b1100100010101111110110111001000 C
b101100110011101100001000000000 9
b11100001001011001100111011000010 %
b11100001001011001100111011000010 2
b11100001001011001100111011000010 @
b10110 /
b10110 0
#270000
05
b1000000111110101111111110000001 ;
0:
b111110 -
16
1=
b1001010000001111101101010010100 "
b1001010000001111101101010010100 7
0<
b10000000000000000000000000000000 $
b10000000000000000000000000000000 ?
b0 8
0>
b1 &
b1 3
b1 A
b1 H
b10111111000001010000000001111110 '
b10111111000001010000000001111110 4
b10111111000001010000000001111110 C
b10000000000000000000000000000000 9
b1001000011001101101100010010 %
b1001000011001101101100010010 2
b1001000011001101101100010010 @
b10111 /
b10111 0
#280000
b10110000101000000100100101100 ;
b111111010 8
b1000000 -
b100101111001101001100001001100 "
b100101111001101001100001001100 7
b100101111001101001100001001100 $
b100101111001101001100001001100 ?
b0 &
b0 3
b0 A
b0 H
b11101001111010111111011011010011 '
b11101001111010111111011011010011 4
b11101001111010111111011011010011 C
b1111000111110000000000000000000 9
b1111110100101000111100011111 %
b1111110100101000111100011111 2
b1111110100101000111100011111 @
b11000 /
b11000 0
#290000
06
1<
b11011011011101001011010010110110 ;
b1000010 -
0=
b1001010011110000111000010010 "
b1001010011110000111000010010 7
b0 $
b0 ?
b101101110110100101100 8
b10 &
b10 3
b10 A
b10 H
b100100100010110100101101001001 '
b100100100010110100101101001001 4
b100100100010110100101101001001 C
b10110100101100101011011000000000 9
b101101110110100101100101011011 %
b101101110110100101100101011011 2
b101101110110100101100101011011 @
b11001 /
b11001 0
#300000
1:
16
0<
b1000100 -
b11000011001111110011100010000110 ;
1=
b11101111010101001001101111011110 "
b11101111010101001001101111011110 7
b11101111001010100101101111011110 $
b11101111001010100101101111011110 ?
b101100000101010110001101 8
b100 &
b100 3
b100 A
b100 H
0(
b11000011001111110011100010000110 '
b11000011001111110011100010000110 4
b11000011001111110011100010000110 C
b101010110001101011000000000 9
b101100000101010110001101011000 %
b101100000101010110001101011000 2
b101100000101010110001101011000 @
b11010 /
b11010 0
#310000
1:
b1000111 -
16
b1 #
b1 F
b1 U
b1101100100000100100001111011001 ;
b11101001101101111101110111010100 "
b11101001101101111101110111010100 7
0<
b1 $
b1 ?
b1111101001101011001100111 8
b11 &
b11 3
b11 A
b11 H
1(
b10010011011111011011110000100110 '
b10010011011111011011110000100110 4
b10010011011111011011110000100110 C
b1001101011001100111111010000000 9
b1111101001101011001100111111010 %
b1111101001101011001100111111010 2
b1111101001101011001100111111010 @
b11011 /
b11011 0
#320000
15
b100110001011010110110101001100 ;
1:
b1001001 -
16
b0 #
b0 F
b0 U
b10111101110001110001010101111100 "
b10111101110001110001010101111100 7
0<
b10110001101101001100010101100011 $
b10110001101101001100010101100011 ?
b1001011110011 8
1>
b100 &
b100 3
b100 A
b100 H
b11011001110100101001001010110011 '
b11011001110100101001001010110011 4
b11011001110100101001001010110011 C
b1000001011110000000000000000000 9
b10010111100110011010100000101111 %
b10010111100110011010100000101111 2
b10010111100110011010100000101111 @
b11100 /
b11100 0
#330000
05
0:
06
1<
b1001011 -
b11100101100110110011011011001011 ;
b1100001100101000011010011000010 "
b1100001100101000011010011000010 7
b0 $
b0 ?
b11110111111100011111 8
0>
b10 &
b10 3
b10 A
b10 H
0(
b11100101100110110011011011001011 '
b11100101100110110011011011001011 4
b11100101100110110011011011001011 C
b11000111111011111011100000000000 9
b1111011111110001111110111110111 %
b1111011111110001111110111110111 2
b1111011111110001111110111110111 @
b11101 /
b11101 0
#340000
0:
b1001101 -
06
b11110110100000101110001011101101 ;
b1011010100101010010000010110 "
b1011010100101010010000010110 7
1<
b1010011001111110 $
b1010011001111110 ?
b1010011001111110 8
b101 &
b101 3
b101 A
b101 H
b11110110100000101110001011101101 '
b11110110100000101110001011101101 4
b11110110100000101110001011101101 C
b11111000001001010010000000000000 9
b10100110011111100000100101001 %
b10100110011111100000100101001 2
b10100110011111100000100101001 @
b11110 /
b11110 0
#350000
15
16
0<
1:
b1010000 -
b10000010000010110101100100000 ;
b11101010110011000100110111010110 "
b11101010110011000100110111010110 7
b11001010110010111000100110010101 $
b11001010110010111000100110010101 ?
b1 8
1>
b100 &
b100 3
b100 A
b100 H
1(
b11101111101111101001010011011111 '
b11101111101111101001010011011111 4
b11101111101111101001010011011111 C
b10000000000000000000000000000000 9
b11011010100010101110001010110101 %
b11011010100010101110001010110101 2
b11011010100010101110001010110101 @
b11111 /
b11111 0
#360000
06
1<
b11101010111101101111010011010101 ;
b1110100001110100000011 8
b1010010 -
0=
b11010011011010110000000110100110 "
b11010011011010110000000110100110 7
b11101010111101101111110011010101 $
b11101010111101101111110011010101 ?
b110 &
b110 3
b110 A
b110 H
b10101000010010000101100101010 '
b10101000010010000101100101010 4
b10101000010010000101100101010 C
b11010000001100110100000000000000 9
b11101000011101000000110011010000 %
b11101000011101000000110011010000 2
b11101000011101000000110011010000 @
b100000 /
b100000 0
#370000
16
05
0<
b110010101000010100001101100101 ;
1:
b1010100 -
b1 #
b1 F
b1 U
1=
b10100000111111101111000101000010 "
b10100000111111101111000101000010 7
b1 $
b1 ?
b11011 8
0>
b11 &
b11 3
b11 A
b11 H
b11001101010111101011110010011010 '
b11001101010111101011110010011010 4
b11001101010111101011110010011010 C
b1110000000000000000000000000000 9
b1101110010111011010110111011100 %
b1101110010111011010110111011100 2
b1101110010111011010110111011100 @
b100001 /
b100001 0
#380000
06
1<
b11011000100001100001011010110001 ;
0:
b1010110 -
b0 #
b0 F
b0 U
0=
b11100101010000010000001000 "
b11100101010000010000001000 7
b0 $
b0 ?
b1010110000111011 8
b10 &
b10 3
b10 A
b10 H
b100111011110011110100101001110 '
b100111011110011110100101001110 4
b100111011110011110100101001110 C
b10111011010101011000000000000000 9
b101011000011101110110101010110 %
b101011000011101110110101010110 2
b101011000011101110110101010110 @
b100010 /
b100010 0
#390000
1:
16
0<
b1100011111100010111010111000111 ;
b1011000 -
1=
b10111111011000010010111101111110 "
b10111111011000010010111101111110 7
b10111111011000010010111101111110 $
b10111111011000010010111101111110 ?
b1011011 8
b0 &
b0 3
b0 A
b0 H
b10011100000011101000101000111000 '
b10011100000011101000101000111000 4
b10011100000011101000101000111000 C
b10110110000000000000000000000000 9
b1011011011011111011100110110110 %
b1011011011011111011100110110110 2
b1011011011011111011100110110110 @
b100011 /
b100011 0
