sim/v002_icg/icg_cell.v
///////////////////////////////////////////
// icg_cell.v — Behavioral Latch-Based Integrated Clock Gating Cell
//
// This is the physically correct ICG implementation.
// The negative-level-sensitive latch holds the enable signal stable
// while the clock is HIGH, preventing glitches.
// The AND gate produces the gated clock.
//
// In a real ASIC flow, this would be mapped to sky130_fd_sc_hd__dlclkp.
///////////////////////////////////////////

module icg_cell (
  input  wire clk_in,
  input  wire enable,
  input  wire test_en,
  output wire clk_out
);

  reg en_latch;

  // Negative level-sensitive latch
  // Transparent when clk_in is LOW, holds when clk_in is HIGH
  always @(*) begin
    if (!clk_in)
      en_latch = enable | test_en;
  end

  // Gated clock output
  assign clk_out = clk_in & en_latch;

endmodule

sim/v002_icg/regfile_icg.v
///////////////////////////////////////////
// regfile_icg.v — Wally regfile with Latch-Based ICG
//
// v002: Modified register file that uses an ICG cell to gate the
// clock to the register array. The clock only reaches the FFs
// when we3 (write enable) is asserted.
//
// This is the key power optimization: during idle cycles (no write),
// the gated clock does not toggle, so 992 flip-flops consume
// near-zero dynamic power.
///////////////////////////////////////////

module regfile_icg #(
  parameter XLEN = 32,
  parameter E_SUPPORTED = 0
) (
  input  wire             clk,
  input  wire             reset,
  input  wire             we3,
  input  wire [4:0]       a1, a2, a3,
  input  wire [XLEN-1:0]  wd3,
  output wire [XLEN-1:0]  rd1, rd2
);

  localparam NUMREGS = E_SUPPORTED ? 16 : 32;

  reg [XLEN-1:0] rf [1:NUMREGS-1];
  integer i;

  // ICG: Gate the clock to the register file
  // The enable signal is (we3 || reset) because we need the clock
  // during reset to clear all registers.
  wire rf_clk_en = we3 | reset;
  wire gated_clk;

  icg_cell u_icg (
    .clk_in  (clk),
    .enable  (rf_clk_en),
    .test_en (1'b0),
    .clk_out (gated_clk)
  );

  // Register file now uses the GATED clock
  always @(negedge gated_clk) begin
    if (reset) begin
      for (i = 1; i < NUMREGS; i = i + 1)
        rf[i] <= {XLEN{1'b0}};
    end else begin
      if (we3 && a3 != 0)
        rf[a3] <= wd3;
    end
  end

  assign rd1 = (a1 != 0) ? rf[a1] : {XLEN{1'b0}};
  assign rd2 = (a2 != 0) ? rf[a2] : {XLEN{1'b0}};

endmodule

sim/v002_icg/tb_regfile_icg.v
///////////////////////////////////////////
// tb_regfile_icg.v — Testbench for ICG-gated regfile (v002)
//
// Same test sequence as v001 baseline, but now monitors gated_clk
// to count how many cycles the register file clock actually toggles.
///////////////////////////////////////////
`timescale 1ns/1ps

module tb_regfile_icg;

  parameter XLEN = 32;
  parameter E_SUPPORTED = 0;

  reg              clk, reset;
  reg              we3;
  reg  [4:0]       a1, a2, a3;
  reg  [XLEN-1:0]  wd3;
  wire [XLEN-1:0]  rd1, rd2;

  // Clock generation: 100 MHz
  initial clk = 0;
  always #5 clk = ~clk;

  // DUT — ICG-gated regfile
  regfile_icg #(.XLEN(XLEN), .E_SUPPORTED(E_SUPPORTED)) dut (
    .clk(clk),
    .reset(reset),
    .we3(we3),
    .a1(a1), .a2(a2), .a3(a3),
    .wd3(wd3),
    .rd1(rd1), .rd2(rd2)
  );

  integer write_cycles;
  integer idle_cycles;
  integer total_cycles;
  integer gated_clk_toggles;
  integer errors;
  integer i;

  // Count gated clock rising edges
  reg prev_gated_clk;
  always @(posedge clk) begin
    prev_gated_clk <= dut.gated_clk;
  end

  // Count falling edges of gated_clk (since regfile writes on negedge)
  always @(negedge dut.gated_clk) begin
    if (!reset)
      gated_clk_toggles = gated_clk_toggles + 1;
  end

  initial begin
    $dumpfile("v002_icg.vcd");
    $dumpvars(0, tb_regfile_icg);

    write_cycles = 0;
    idle_cycles = 0;
    total_cycles = 0;
    gated_clk_toggles = 0;
    errors = 0;
    reset = 1;
    we3 = 0;
    a1 = 0; a2 = 0; a3 = 0;
    wd3 = 0;
    prev_gated_clk = 0;

    repeat(4) @(posedge clk);
    reset = 0;
    @(posedge clk);

    $display("========================================");
    $display("v002 ICG-GATED REGFILE SIMULATION START");
    $display("XLEN=%0d  NUMREGS=%0d", XLEN, E_SUPPORTED ? 16 : 32);
    $display("========================================");

    // TEST 1: Write to all 31 registers
    $display("[TEST 1] Writing all registers x1-x31...");
    for (i = 1; i < 32; i = i + 1) begin
      @(negedge clk);
      we3 = 1;
      a3 = i[4:0];
      wd3 = 32'hA000_0000 + i;
      write_cycles = write_cycles + 1;
      total_cycles = total_cycles + 1;
      @(posedge clk);
    end
    we3 = 0;
    @(posedge clk);

    // TEST 2: Read back and verify
    $display("[TEST 2] Reading back and verifying...");
    for (i = 1; i < 32; i = i + 1) begin
      a1 = i[4:0];
      a2 = 5'd0;
      #1;
      if (rd1 !== (32'hA000_0000 + i)) begin
        $display("  ERROR: x%0d = 0x%08h, expected 0x%08h", i, rd1, 32'hA000_0000 + i);
        errors = errors + 1;
      end
      if (rd2 !== 32'h0) begin
        $display("  ERROR: x0 read as 0x%08h, expected 0x00000000", rd2);
        errors = errors + 1;
      end
      @(posedge clk);
      idle_cycles = idle_cycles + 1;
      total_cycles = total_cycles + 1;
    end

    // TEST 3: Stress
    $display("[TEST 3] Rapid write/read stress...");
    for (i = 1; i < 16; i = i + 1) begin
      @(negedge clk);
      we3 = 1;
      a3 = i[4:0];
      wd3 = 32'hDEAD_0000 + i;
      write_cycles = write_cycles + 1;
      total_cycles = total_cycles + 1;
      @(posedge clk);
      we3 = 0;
      a1 = i[4:0];
      #1;
      if (rd1 !== (32'hDEAD_0000 + i)) begin
        $display("  ERROR: x%0d = 0x%08h, expected 0x%08h", i, rd1, 32'hDEAD_0000 + i);
        errors = errors + 1;
      end
      @(posedge clk);
      idle_cycles = idle_cycles + 1;
      total_cycles = total_cycles + 1;
    end

    // TEST 4: 50 idle cycles
    $display("[TEST 4] 50 idle cycles (gated_clk should NOT toggle)...");
    we3 = 0;
    a1 = 5'd1; a2 = 5'd2;
    repeat(50) begin
      @(posedge clk);
      idle_cycles = idle_cycles + 1;
      total_cycles = total_cycles + 1;
    end

    // Summary
    $display("========================================");
    $display("v002 ICG-GATED SIMULATION RESULTS");
    $display("========================================");
    $display("Total main clk cycles:   %0d", total_cycles);
    $display("Write cycles (we3=1):    %0d", write_cycles);
    $display("Idle cycles  (we3=0):    %0d", idle_cycles);
    $display("Gated clk negedge count: %0d", gated_clk_toggles);
    $display("Write activity (%%):      %0d%%", (write_cycles * 100) / total_cycles);
    $display("Clock gating efficiency: %0d%%",
      ((total_cycles - gated_clk_toggles) * 100) / total_cycles);
    $display("Errors:                  %0d", errors);
    if (errors == 0)
      $display("STATUS: PASS");
    else
      $display("STATUS: FAIL");
    $display("========================================");
    $display("POWER IMPACT: In baseline, 992 FFs toggle every cycle.");
    $display("With ICG, 992 FFs only toggle %0d/%0d cycles = %0d%% of the time.",
      gated_clk_toggles, total_cycles,
      (gated_clk_toggles * 100) / total_cycles);
    $display("========================================");

    #20;
    $finish;
  end

endmodule

sim/v002_icg/v002_icg.vcd
$date
	Tue Jul 21 13:15:03 2026
$end
$version
	Icarus Verilog
$end
$timescale
	1ps
$end
$scope module tb_regfile_icg $end
$var wire 32 ! rd2 [31:0] $end
$var wire 32 " rd1 [31:0] $end
$var reg 5 # a1 [4:0] $end
$var reg 5 $ a2 [4:0] $end
$var reg 5 % a3 [4:0] $end
$var reg 1 & clk $end
$var reg 1 ' prev_gated_clk $end
$var reg 1 ( reset $end
$var reg 32 ) wd3 [31:0] $end
$var reg 1 * we3 $end
$var integer 32 + errors [31:0] $end
$var integer 32 , gated_clk_toggles [31:0] $end
$var integer 32 - i [31:0] $end
$var integer 32 . idle_cycles [31:0] $end
$var integer 32 / total_cycles [31:0] $end
$var integer 32 0 write_cycles [31:0] $end
$scope module dut $end
$var wire 5 1 a1 [4:0] $end
$var wire 5 2 a2 [4:0] $end
$var wire 5 3 a3 [4:0] $end
$var wire 1 & clk $end
$var wire 1 ( reset $end
$var wire 1 4 rf_clk_en $end
$var wire 32 5 wd3 [31:0] $end
$var wire 1 * we3 $end
$var wire 32 6 rd2 [31:0] $end
$var wire 32 7 rd1 [31:0] $end
$var wire 1 8 gated_clk $end
$var integer 32 9 i [31:0] $end
$scope module u_icg $end
$var wire 1 & clk_in $end
$var wire 1 8 clk_out $end
$var wire 1 4 enable $end
$var wire 1 : test_en $end
$var reg 1 ; en_latch $end
$upscope $end
$upscope $end
$upscope $end
$enddefinitions $end
#0
$dumpvars
1;
0:
b100000 9
08
b0 7
b0 6
b0 5
14
b0 3
b0 2
b0 1
b0 0
b0 /
b0 .
bx -
b0 ,
b0 +
0*
b0 )
1(
0'
0&
b0 %
b0 $
b0 #
b0 "
b0 !
$end
#5000
18
1&
#10000
b100000 9
08
0&
#15000
18
1&
#20000
b100000 9
08
0&
#25000
18
1&
#30000
b100000 9
08
0&
#35000
04
18
0(
1&
#40000
b1 ,
08
0;
0&
#45000
b1 -
1&
#50000
1;
14
b1 /
b1 0
b10100000000000000000000000000001 )
b10100000000000000000000000000001 5
b1 %
b1 3
1*
0&
#55000
18
b10 -
1&
#60000
b10 ,
08
b10 /
b10 0
b10100000000000000000000000000010 )
b10100000000000000000000000000010 5
b10 %
b10 3
0&
#65000
18
b11 -
1&
#70000
b11 ,
08
b11 /
b11 0
b10100000000000000000000000000011 )
b10100000000000000000000000000011 5
b11 %
b11 3
0&
#75000
18
b100 -
1&
#80000
b100 ,
08
b100 /
b100 0
b10100000000000000000000000000100 )
b10100000000000000000000000000100 5
b100 %
b100 3
0&
#85000
18
b101 -
1&
#90000
b101 ,
08
b101 /
b101 0
b10100000000000000000000000000101 )
b10100000000000000000000000000101 5
b101 %
b101 3
0&
#95000
18
b110 -
1&
#100000
b110 ,
08
b110 /
b110 0
b10100000000000000000000000000110 )
b10100000000000000000000000000110 5
b110 %
b110 3
0&
#105000
18
b111 -
1&
#110000
b111 ,
08
b111 /
b111 0
b10100000000000000000000000000111 )
b10100000000000000000000000000111 5
b111 %
b111 3
0&
#115000
18
b1000 -
1&
#120000
b1000 ,
08
b1000 /
b1000 0
b10100000000000000000000000001000 )
b10100000000000000000000000001000 5
b1000 %
b1000 3
0&
#125000
18
b1001 -
1&
#130000
b1001 ,
08
b1001 /
b1001 0
b10100000000000000000000000001001 )
b10100000000000000000000000001001 5
b1001 %
b1001 3
0&
#135000
18
b1010 -
1&
#140000
b1010 ,
08
b1010 /
b1010 0
b10100000000000000000000000001010 )
b10100000000000000000000000001010 5
b1010 %
b1010 3
0&
#145000
18
b1011 -
1&
#150000
b1011 ,
08
b1011 /
b1011 0
b10100000000000000000000000001011 )
b10100000000000000000000000001011 5
b1011 %
b1011 3
0&
#155000
18
b1100 -
1&
#160000
b1100 ,
08
b1100 /
b1100 0
b10100000000000000000000000001100 )
b10100000000000000000000000001100 5
b1100 %
b1100 3
0&
#165000
18
b1101 -
1&
#170000
b1101 ,
08
b1101 /
b1101 0
b10100000000000000000000000001101 )
b10100000000000000000000000001101 5
b1101 %
b1101 3
0&
#175000
18
b1110 -
1&
#180000
b1110 ,
08
b1110 /
b1110 0
b10100000000000000000000000001110 )
b10100000000000000000000000001110 5
b1110 %
b1110 3
0&
#185000
18
b1111 -
1&
#190000
b1111 ,
08
b1111 /
b1111 0
b10100000000000000000000000001111 )
b10100000000000000000000000001111 5
b1111 %
b1111 3
0&
#195000
18
b10000 -
1&
#200000
b10000 ,
08
b10000 /
b10000 0
b10100000000000000000000000010000 )
b10100000000000000000000000010000 5
b10000 %
b10000 3
0&
#205000
18
b10001 -
1&
#210000
b10001 ,
08
b10001 /
b10001 0
b10100000000000000000000000010001 )
b10100000000000000000000000010001 5
b10001 %
b10001 3
0&
#215000
18
b10010 -
1&
#220000
b10010 ,
08
b10010 /
b10010 0
b10100000000000000000000000010010 )
b10100000000000000000000000010010 5
b10010 %
b10010 3
0&
#225000
18
b10011 -
1&
#230000
b10011 ,
08
b10011 /
b10011 0
b10100000000000000000000000010011 )
b10100000000000000000000000010011 5
b10011 %
b10011 3
0&
#235000
18
b10100 -
1&
#240000
b10100 ,
08
b10100 /
b10100 0
b10100000000000000000000000010100 )
b10100000000000000000000000010100 5
b10100 %
b10100 3
0&
#245000
18
b10101 -
1&
#250000
b10101 ,
08
b10101 /
b10101 0
b10100000000000000000000000010101 )
b10100000000000000000000000010101 5
b10101 %
b10101 3
0&
#255000
18
b10110 -
1&
#260000
b10110 ,
08
b10110 /
b10110 0
b10100000000000000000000000010110 )
b10100000000000000000000000010110 5
b10110 %
b10110 3
0&
#265000
18
b10111 -
1&
#270000
b10111 ,
08
b10111 /
b10111 0
b10100000000000000000000000010111 )
b10100000000000000000000000010111 5
b10111 %
b10111 3
0&
#275000
18
b11000 -
1&
#280000
b11000 ,
08
b11000 /
b11000 0
b10100000000000000000000000011000 )
b10100000000000000000000000011000 5
b11000 %
b11000 3
0&
#285000
18
b11001 -
1&
#290000
b11001 ,
08
b11001 /
b11001 0
b10100000000000000000000000011001 )
b10100000000000000000000000011001 5
b11001 %
b11001 3
0&
#295000
18
b11010 -
1&
#300000
b11010 ,
08
b11010 /
b11010 0
b10100000000000000000000000011010 )
b10100000000000000000000000011010 5
b11010 %
b11010 3
0&
#305000
18
b11011 -
1&
#310000
b11011 ,
08
b11011 /
b11011 0
b10100000000000000000000000011011 )
b10100000000000000000000000011011 5
b11011 %
b11011 3
0&
#315000
18
b11100 -
1&
#320000
b11100 ,
08
b11100 /
b11100 0
b10100000000000000000000000011100 )
b10100000000000000000000000011100 5
b11100 %
b11100 3
0&
#325000
18
b11101 -
1&
#330000
b11101 ,
08
b11101 /
b11101 0
b10100000000000000000000000011101 )
b10100000000000000000000000011101 5
b11101 %
b11101 3
0&
#335000
18
b11110 -
1&
#340000
b11110 ,
08
b11110 /
b11110 0
b10100000000000000000000000011110 )
b10100000000000000000000000011110 5
b11110 %
b11110 3
0&
#345000
18
b11111 -
1&
#350000
b11111 ,
08
b11111 /
b11111 0
b10100000000000000000000000011111 )
b10100000000000000000000000011111 5
b11111 %
b11111 3
0&
#355000
04
18
0*
b100000 -
1&
#360000
b100000 ,
08
0;
0&
#365000
b1 #
b1 1
b1 -
1&
#366000
b1 +
#370000
0&
#375000
b10100000000000000000000000000010 "
b10100000000000000000000000000010 7
b10 #
b10 1
b10 -
b100000 /
b1 .
1&
#380000
0&
#385000
b10100000000000000000000000000011 "
b10100000000000000000000000000011 7
b11 #
b11 1
b11 -
b100001 /
b10 .
1&
#390000
0&
#395000
b10100000000000000000000000000100 "
b10100000000000000000000000000100 7
b100 #
b100 1
b100 -
b100010 /
b11 .
1&
#400000
0&
#405000
b10100000000000000000000000000101 "
b10100000000000000000000000000101 7
b101 #
b101 1
b101 -
b100011 /
b100 .
1&
#410000
0&
#415000
b10100000000000000000000000000110 "
b10100000000000000000000000000110 7
b110 #
b110 1
b110 -
b100100 /
b101 .
1&
#420000
0&
#425000
b10100000000000000000000000000111 "
b10100000000000000000000000000111 7
b111 #
b111 1
b111 -
b100101 /
b110 .
1&
#430000
0&
#435000
b10100000000000000000000000001000 "
b10100000000000000000000000001000 7
b1000 #
b1000 1
b1000 -
b100110 /
b111 .
1&
#440000
0&
#445000
b10100000000000000000000000001001 "
b10100000000000000000000000001001 7
b1001 #
b1001 1
b1001 -
b100111 /
b1000 .
1&
#450000
0&
#455000
b10100000000000000000000000001010 "
b10100000000000000000000000001010 7
b1010 #
b1010 1
b1010 -
b101000 /
b1001 .
1&
#460000
0&
#465000
b10100000000000000000000000001011 "
b10100000000000000000000000001011 7
b1011 #
b1011 1
b1011 -
b101001 /
b1010 .
1&
#470000
0&
#475000
b10100000000000000000000000001100 "
b10100000000000000000000000001100 7
b1100 #
b1100 1
b1100 -
b101010 /
b1011 .
1&
#480000
0&
#485000
b10100000000000000000000000001101 "
b10100000000000000000000000001101 7
b1101 #
b1101 1
b1101 -
b101011 /
b1100 .
1&
#490000
0&
#495000
b10100000000000000000000000001110 "
b10100000000000000000000000001110 7
b1110 #
b1110 1
b1110 -
b101100 /
b1101 .
1&
#500000
0&
#505000
b10100000000000000000000000001111 "
b10100000000000000000000000001111 7
b1111 #
b1111 1
b1111 -
b101101 /
b1110 .
1&
#510000
0&
#515000
b10100000000000000000000000010000 "
b10100000000000000000000000010000 7
b10000 #
b10000 1
b10000 -
b101110 /
b1111 .
1&
#520000
0&
#525000
b10100000000000000000000000010001 "
b10100000000000000000000000010001 7
b10001 #
b10001 1
b10001 -
b101111 /
b10000 .
1&
#530000
0&
#535000
b10100000000000000000000000010010 "
b10100000000000000000000000010010 7
b10010 #
b10010 1
b10010 -
b110000 /
b10001 .
1&
#540000
0&
#545000
b10100000000000000000000000010011 "
b10100000000000000000000000010011 7
b10011 #
b10011 1
b10011 -
b110001 /
b10010 .
1&
#550000
0&
#555000
b10100000000000000000000000010100 "
b10100000000000000000000000010100 7
b10100 #
b10100 1
b10100 -
b110010 /
b10011 .
1&
#560000
0&
#565000
b10100000000000000000000000010101 "
b10100000000000000000000000010101 7
b10101 #
b10101 1
b10101 -
b110011 /
b10100 .
1&
#570000
0&
#575000
b10100000000000000000000000010110 "
b10100000000000000000000000010110 7
b10110 #
b10110 1
b10110 -
b110100 /
b10101 .
1&
#580000
0&
#585000
b10100000000000000000000000010111 "
b10100000000000000000000000010111 7
b10111 #
b10111 1
b10111 -
b110101 /
b10110 .
1&
#590000
0&
#595000
b10100000000000000000000000011000 "
b10100000000000000000000000011000 7
b11000 #
b11000 1
b11000 -
b110110 /
b10111 .
1&
#600000
0&
#605000
b10100000000000000000000000011001 "
b10100000000000000000000000011001 7
b11001 #
b11001 1
b11001 -
b110111 /
b11000 .
1&
#610000
0&
#615000
b10100000000000000000000000011010 "
b10100000000000000000000000011010 7
b11010 #
b11010 1
b11010 -
b111000 /
b11001 .
1&
#620000
0&
#625000
b10100000000000000000000000011011 "
b10100000000000000000000000011011 7
b11011 #
b11011 1
b11011 -
b111001 /
b11010 .
1&
#630000
0&
#635000
b10100000000000000000000000011100 "
b10100000000000000000000000011100 7
b11100 #
b11100 1
b11100 -
b111010 /
b11011 .
1&
#640000
0&
#645000
b10100000000000000000000000011101 "
b10100000000000000000000000011101 7
b11101 #
b11101 1
b11101 -
b111011 /
b11100 .
1&
#650000
0&
#655000
b10100000000000000000000000011110 "
b10100000000000000000000000011110 7
b11110 #
b11110 1
b11110 -
b111100 /
b11101 .
1&
#660000
0&
#665000
b10100000000000000000000000011111 "
b10100000000000000000000000011111 7
b11111 #
b11111 1
b11111 -
b111101 /
b11110 .
1&
#670000
0&
#675000
b1 -
b111110 /
b11111 .
1&
#680000
1;
14
b111111 /
b100000 0
b11011110101011010000000000000001 )
b11011110101011010000000000000001 5
b1 %
b1 3
1*
0&
#685000
b0 "
b0 7
04
18
b1 #
b1 1
0*
1&
#686000
b10 +
#690000
b100001 ,
08
0;
0&
#695000
b10 -
b1000000 /
b100000 .
1&
#700000
1;
14
b1000001 /
b100001 0
b11011110101011010000000000000010 )
b11011110101011010000000000000010 5
b10 %
b10 3
1*
0&
#705000
b10100000000000000000000000000010 "
b10100000000000000000000000000010 7
04
18
b10 #
b10 1
0*
1&
#706000
b11 +
#710000
b100010 ,
08
0;
0&
#715000
b11 -
b1000010 /
b100001 .
1&
#720000
1;
14
b1000011 /
b100010 0
b11011110101011010000000000000011 )
b11011110101011010000000000000011 5
b11 %
b11 3
1*
0&
#725000
b10100000000000000000000000000011 "
b10100000000000000000000000000011 7
04
18
b11 #
b11 1
0*
1&
#726000
b100 +
#730000
b100011 ,
08
0;
0&
#735000
b100 -
b1000100 /
b100010 .
1&
#740000
1;
14
b1000101 /
b100011 0
b11011110101011010000000000000100 )
b11011110101011010000000000000100 5
b100 %
b100 3
1*
0&
#745000
b10100000000000000000000000000100 "
b10100000000000000000000000000100 7
04
18
b100 #
b100 1
0*
1&
#746000
b101 +
#750000
b100100 ,
08
0;
0&
#755000
b101 -
b1000110 /
b100011 .
1&
#760000
1;
14
b1000111 /
b100100 0
b11011110101011010000000000000101 )
b11011110101011010000000000000101 5
b101 %
b101 3
1*
0&
#765000
b10100000000000000000000000000101 "
b10100000000000000000000000000101 7
04
18
b101 #
b101 1
0*
1&
#766000
b110 +
#770000
b100101 ,
08
0;
0&
#775000
b110 -
b1001000 /
b100100 .
1&
#780000
1;
14
b1001001 /
b100101 0
b11011110101011010000000000000110 )
b11011110101011010000000000000110 5
b110 %
b110 3
1*
0&
#785000
b10100000000000000000000000000110 "
b10100000000000000000000000000110 7
04
18
b110 #
b110 1
0*
1&
#786000
b111 +
#790000
b100110 ,
08
0;
0&
#795000
b111 -
b1001010 /
b100101 .
1&
#800000
1;
14
b1001011 /
b100110 0
b11011110101011010000000000000111 )
b11011110101011010000000000000111 5
b111 %
b111 3
1*
0&
#805000
b10100000000000000000000000000111 "
b10100000000000000000000000000111 7
04
18
b111 #
b111 1
0*
1&
#806000
b1000 +
#810000
b100111 ,
08
0;
0&
#815000
b1000 -
b1001100 /
b100110 .
1&
#820000
1;
14
b1001101 /
b100111 0
b11011110101011010000000000001000 )
b11011110101011010000000000001000 5
b1000 %
b1000 3
1*
0&
#825000
b10100000000000000000000000001000 "
b10100000000000000000000000001000 7
04
18
b1000 #
b1000 1
0*
1&
#826000
b1001 +
#830000
b101000 ,
08
0;
0&
#835000
b1001 -
b1001110 /
b100111 .
1&
#840000
1;
14
b1001111 /
b101000 0
b11011110101011010000000000001001 )
b11011110101011010000000000001001 5
b1001 %
b1001 3
1*
0&
#845000
b10100000000000000000000000001001 "
b10100000000000000000000000001001 7
04
18
b1001 #
b1001 1
0*
1&
#846000
b1010 +
#850000
b101001 ,
08
0;
0&
#855000
b1010 -
b1010000 /
b101000 .
1&
#860000
1;
14
b1010001 /
b101001 0
b11011110101011010000000000001010 )
b11011110101011010000000000001010 5
b1010 %
b1010 3
1*
0&
#865000
b10100000000000000000000000001010 "
b10100000000000000000000000001010 7
04
18
b1010 #
b1010 1
0*
1&
#866000
b1011 +
#870000
b101010 ,
08
0;
0&
#875000
b1011 -
b1010010 /
b101001 .
1&
#880000
1;
14
b1010011 /
b101010 0
b11011110101011010000000000001011 )
b11011110101011010000000000001011 5
b1011 %
b1011 3
1*
0&
#885000
b10100000000000000000000000001011 "
b10100000000000000000000000001011 7
04
18
b1011 #
b1011 1
0*
1&
#886000
b1100 +
#890000
b101011 ,
08
0;
0&
#895000
b1100 -
b1010100 /
b101010 .
1&
#900000
1;
14
b1010101 /
b101011 0
b11011110101011010000000000001100 )
b11011110101011010000000000001100 5
b1100 %
b1100 3
1*
0&
#905000
b10100000000000000000000000001100 "
b10100000000000000000000000001100 7
04
18
b1100 #
b1100 1
0*
1&
#906000
b1101 +
#910000
b101100 ,
08
0;
0&
#915000
b1101 -
b1010110 /
b101011 .
1&
#920000
1;
14
b1010111 /
b101100 0
b11011110101011010000000000001101 )
b11011110101011010000000000001101 5
b1101 %
b1101 3
1*
0&
#925000
b10100000000000000000000000001101 "
b10100000000000000000000000001101 7
04
18
b1101 #
b1101 1
0*
1&
#926000
b1110 +
#930000
b101101 ,
08
0;
0&
#935000
b1110 -
b1011000 /
b101100 .
1&
#940000
1;
14
b1011001 /
b101101 0
b11011110101011010000000000001110 )
b11011110101011010000000000001110 5
b1110 %
b1110 3
1*
0&
#945000
b10100000000000000000000000001110 "
b10100000000000000000000000001110 7
04
18
b1110 #
b1110 1
0*
1&
#946000
b1111 +
#950000
b101110 ,
08
0;
0&
#955000
b1111 -
b1011010 /
b101101 .
1&
#960000
1;
14
b1011011 /
b101110 0
b11011110101011010000000000001111 )
b11011110101011010000000000001111 5
b1111 %
b1111 3
1*
0&
#965000
b10100000000000000000000000001111 "
b10100000000000000000000000001111 7
04
18
b1111 #
b1111 1
0*
1&
#966000
b10000 +
#970000
b101111 ,
08
0;
0&
#975000
b10100000000000000000000000000010 !
b10100000000000000000000000000010 6
b0 "
b0 7
b10 $
b10 2
b1 #
b1 1
b10000 -
b1011100 /
b101110 .
1&
#980000
0&
#985000
b1011101 /
b101111 .
1&
#990000
0&
#995000
b1011110 /
b110000 .
1&
#1000000
0&
#1005000
b1011111 /
b110001 .
1&
#1010000
0&
#1015000
b1100000 /
b110010 .
1&
#1020000
0&
#1025000
b1100001 /
b110011 .
1&
#1030000
0&
#1035000
b1100010 /
b110100 .
1&
#1040000
0&
#1045000
b1100011 /
b110101 .
1&
#1050000
0&
#1055000
b1100100 /
b110110 .
1&
#1060000
0&
#1065000
b1100101 /
b110111 .
1&
#1070000
0&
#1075000
b1100110 /
b111000 .
1&
#1080000
0&
#1085000
b1100111 /
b111001 .
1&
#1090000
0&
#1095000
b1101000 /
b111010 .
1&
#1100000
0&
#1105000
b1101001 /
b111011 .
1&
#1110000
0&
#1115000
b1101010 /
b111100 .
1&
#1120000
0&
#1125000
b1101011 /
b111101 .
1&
#1130000
0&
#1135000
b1101100 /
b111110 .
1&
#1140000
0&
#1145000
b1101101 /
b111111 .
1&
#1150000
0&
#1155000
b1101110 /
b1000000 .
1&
#1160000
0&
#1165000
b1101111 /
b1000001 .
1&
#1170000
0&
#1175000
b1110000 /
b1000010 .
1&
#1180000
0&
#1185000
b1110001 /
b1000011 .
1&
#1190000
0&
#1195000
b1110010 /
b1000100 .
1&
#1200000
0&
#1205000
b1110011 /
b1000101 .
1&
#1210000
0&
#1215000
b1110100 /
b1000110 .
1&
#1220000
0&
#1225000
b1110101 /
b1000111 .
1&
#1230000
0&
#1235000
b1110110 /
b1001000 .
1&
#1240000
0&
#1245000
b1110111 /
b1001001 .
1&
#1250000
0&
#1255000
b1111000 /
b1001010 .
1&
#1260000
0&
#1265000
b1111001 /
b1001011 .
1&
#1270000
0&
#1275000
b1111010 /
b1001100 .
1&
#1280000
0&
#1285000
b1111011 /
b1001101 .
1&
#1290000
0&
#1295000
b1111100 /
b1001110 .
1&
#1300000
0&
#1305000
b1111101 /
b1001111 .
1&
#1310000
0&
#1315000
b1111110 /
b1010000 .
1&
#1320000
0&
#1325000
b1111111 /
b1010001 .
1&
#1330000
0&
#1335000
b10000000 /
b1010010 .
1&
#1340000
0&
#1345000
b10000001 /
b1010011 .
1&
#1350000
0&
#1355000
b10000010 /
b1010100 .
1&
#1360000
0&
#1365000
b10000011 /
b1010101 .
1&
#1370000
0&
#1375000
b10000100 /
b1010110 .
1&
#1380000
0&
#1385000
b10000101 /
b1010111 .
1&
#1390000
0&
#1395000
b10000110 /
b1011000 .
1&
#1400000
0&
#1405000
b10000111 /
b1011001 .
1&
#1410000
0&
#1415000
b10001000 /
b1011010 .
1&
#1420000
0&
#1425000
b10001001 /
b1011011 .
1&
#1430000
0&
#1435000
b10001010 /
b1011100 .
1&
#1440000
0&
#1445000
b10001011 /
b1011101 .
1&
#1450000
0&
#1455000
b10001100 /
b1011110 .
1&
#1460000
0&
#1465000
b10001101 /
b1011111 .
1&
#1470000
0&
#1475000
b10001110 /
b1100000 .
1&
